Workbook

Sheet State Mapping
A1: Abbrev | B1: Full State Name
A2: AK | B2: Alaska
A3: AL | B3: Alabama
A4: AR | B4: Arkansas
A5: AZ | B5: Arizona
A6: CA | B6: California
A7: CO | B7: Colorado
A8: CT | B8: Connecticut
A9: DC | B9: District of Columbia
A10: DE | B10: Delaware
A11: FL | B11: Florida
A12: GA | B12: Georgia
... A53: WY | B53: Wyoming

Sheet State Premium Data
A1: state | B1: earnings_hs | C1: earnings_bachelors | D1: premium_dollars | E1: premium_ratio | F1: premium_pct | G1: cost_of_living_index
A2: District of Columbia | B2: 40715 | C2: 95628 | D2: 54913 | E2: 2.35 | F2: 135 | G2: 109.9
A3: New Jersey | B3: 41528 | C3: 80114 | D3: 38586 | E3: 1.93 | F3: 93 | G3: 108.8
A4: California | B4: 40803 | C4: 78278 | D4: 37475 | E4: 1.92 | F4: 92 | G4: 110.7
A5: New York | B5: 39771 | C5: 74504 | D5: 34733 | E5: 1.87 | F5: 87 | G5: 107.9
A6: Massachusetts | B6: 43761 | C6: 79985 | D6: 36224 | E6: 1.83 | F6: 83 | G6: 105.8
A7: Virginia | B7: 41061 | C7: 74468 | D7: 33407 | E7: 1.81 | F7: 81 | G7: 101.1
A8: Puerto Rico | B8: 16957 | C8: 30562 | D8: 13605 | E8: 1.8 | F8: 80
A9: Connecticut | B9: 42120 | C9: 75975 | D9: 33855 | E9: 1.8 | F9: 80 | G9: 103.6
A10: Maryland | B10: 42778 | C10: 76748 | D10: 33970 | E10: 1.79 | F10: 79 | G10: 105
A11: Texas | B11: 37086 | C11: 66474 | D11: 29388 | E11: 1.79 | F11: 79 | G11: 97.1
A12: Illinois | B12: 40285 | C12: 71127 | D12: 30842 | E12: 1.77 | F12: 77 | G12: 100
A13: Michigan | B13: 36823 | C13: 64810 | D13: 27987 | E13: 1.76 | F13: 76 | G13: 96.2
A14: Washington | B14: 44866 | C14: 78485 | D14: 33619 | E14: 1.75 | F14: 75 | G14: 107
A15: Georgia | B15: 36820 | C15: 64185 | D15: 27365 | E15: 1.74 | F15: 74 | G15: 96.3
A16: Colorado | B16: 42541 | C16: 73072 | D16: 30531 | E16: 1.72 | F16: 72 | G16: 103.1
A17: Oregon | B17: 39308 | C17: 67100 | D17: 27792 | E17: 1.71 | F17: 71 | G17: 103.4
A18: Ohio | B18: 37990 | C18: 64933 | D18: 26943 | E18: 1.71 | F18: 71 | G18: 92.8
A19: North Carolina | B19: 36723 | C19: 62338 | D19: 25615 | E19: 1.7 | F19: 70 | G19: 94.3
A20: Minnesota | B20: 42435 | C20: 71254 | D20: 28819 | E20: 1.68 | F20: 68 | G20: 98.6
... A53: Vermont | B53: 43810 | C53: 56741 | D53: 12931 | E53: 1.3 | F53: 30 | G53: 98

Sheet College Data
A1: University | B1: State | C1: City | D1: Admission Rate (%) | E1: Average SAT | F1: Student Size | G1: In-State Tuition ($) | H1: Out-of-State Tuition ($) | I1: Median Earnings 10yr ($) | J1: Completion Rate (%) | K1: Median Debt ($) | L1: Nobel Prizes | M1: March Madness 2026 | N1: State Full Name | O1: State College Wage Premium ($) | P1: State Baseline Earnings - Bachelors ($) | Q1: Debt-to-Premium Ratio | R1: Real Earnings vs State Baseline ($) | S1: Real Earnings vs State Baseline (%)
A2: Stanford University | B2: CA | C2: Stanford | D2: 3.6 | E2: 1553 | F2: 7554 | G2: 65910 | H2: 65910 | I2: 124080 | J2: 92.4 | K2: 12000 | L2: 22 | M2: No | N2: =INDEX('State Mapping'!$B$2:$B$53,MATCH(B2,'State Mapping'!$A$2:$A$53,0)) -> California | O2: =IFERROR(INDEX('State Premium Data'!$D$2:$D$53,MATCH(N2,'State Premium Data'!$A$2:$A$53,0)),"") -> 37475 | P2: =IFERROR(INDEX('State Premium Data'!$C$2:$C$53,MATCH(N2,'State Premium Data'!$A$2:$A$53,0)),"") -> 78278 | Q2: =IFERROR(K2/O2,"") -> 0.32021348 | R2: =IFERROR(I2-P2,"") -> 45802 | S2: =IFERROR(R2/P2,"") -> 0.5851197
A3: Harvard University | B3: MA | C3: Cambridge | D3: 3.6 | E3: 1553 | F3: 7601 | G3: 61676 | H3: 61676 | I3: 101817 | J3: 97.5 | K3: 14000 | L3: 29 | M3: No | N3: =INDEX('State Mapping'!$B$2:$B$53,MATCH(B3,'State Mapping'!$A$2:$A$53,0)) -> Massachusetts | O3: =IFERROR(INDEX('State Premium Data'!$D$2:$D$53,MATCH(N3,'State Premium Data'!$A$2:$A$53,0)),"") -> 36224 | P3: =IFERROR(INDEX('State Premium Data'!$C$2:$C$53,MATCH(N3,'State Premium Data'!$A$2:$A$53,0)),"") -> 79985 | Q3: =IFERROR(K3/O3,"") -> 0.3864841 | R3: =IFERROR(I3-P3,"") -> 21832 | S3: =IFERROR(R3/P3,"") -> 0.27295118
A4: Yale University | B4: CT | C4: New Haven | D4: 3.9 | E4: 1534 | F4: 6758 | G4: 67250 | H4: 67250 | I4: 100533 | J4: 96 | K4: 12975 | L4: 9 | M4: No | N4: =INDEX('State Mapping'!$B$2:$B$53,MATCH(B4,'State Mapping'!$A$2:$A$53,0)) -> Connecticut | O4: =IFERROR(INDEX('State Premium Data'!$D$2:$D$53,MATCH(N4,'State Premium Data'!$A$2:$A$53,0)),"") -> 33855 | P4: =IFERROR(INDEX('State Premium Data'!$C$2:$C$53,MATCH(N4,'State Premium Data'!$A$2:$A$53,0)),"") -> 75975 | Q4: =IFERROR(K4/O4,"") -> 0.3832521 | R4: =IFERROR(I4-P4,"") -> 24558 | S4: =IFERROR(R4/P4,"") -> 0.32323791
A5: Columbia University in the City of New York | B5: NY | C5: New York | D5: 4 | E5: 1553 | F5: 8973 | G5: 71845 | H5: 71845 | I5: 102491 | J5: 95.5 | K5: 21500 | L5: 18 | M5: No | N5: =INDEX('State Mapping'!$B$2:$B$53,MATCH(B5,'State Mapping'!$A$2:$A$53,0)) -> New York | O5: =IFERROR(INDEX('State Premium Data'!$D$2:$D$53,MATCH(N5,'State Premium Data'!$A$2:$A$53,0)),"") -> 34733 | P5: =IFERROR(INDEX('State Premium Data'!$C$2:$C$53,MATCH(N5,'State Premium Data'!$A$2:$A$53,0)),"") -> 74504 | Q5: =IFERROR(K5/O5,"") -> 0.61900786 | R5: =IFERROR(I5-P5,"") -> 27987 | S5: =IFERROR(R5/P5,"") -> 0.37564426
A6: University of Chicago | B6: IL | C6: Chicago | D6: 4.5 | E6: 1554 | F6: 7569 | G6: 70662 | H6: 70662 | I6: 91885 | J6: 95.4 | K6: 15000 | L6: 20 | M6: No | N6: =INDEX('State Mapping'!$B$2:$B$53,MATCH(B6,'State Mapping'!$A$2:$A$53,0)) -> Illinois | O6: =IFERROR(INDEX('State Premium Data'!$D$2:$D$53,MATCH(N6,'State Premium Data'!$A$2:$A$53,0)),"") -> 30842 | P6: =IFERROR(INDEX('State Premium Data'!$C$2:$C$53,MATCH(N6,'State Premium Data'!$A$2:$A$53,0)),"") -> 71127 | Q6: =IFERROR(K6/O6,"") -> 0.48634978 | R6: =IFERROR(I6-P6,"") -> 20758 | S6: =IFERROR(R6/P6,"") -> 0.29184417
A7: Princeton University | B7: NJ | C7: Princeton | D7: 4.6 | E7: 1553 | F7: 5709 | G7: 62688 | H7: 62688 | I7: 110066 | J7: 97.4 | K7: 10320 | L7: 18 | M7: No | N7: =INDEX('State Mapping'!$B$2:$B$53,MATCH(B7,'State Mapping'!$A$2:$A$53,0)) -> New Jersey | O7: =IFERROR(INDEX('State Premium Data'!$D$2:$D$53,MATCH(N7,'State Premium Data'!$A$2:$A$53,0)),"") -> 38586 | P7: =IFERROR(INDEX('State Premium Data'!$C$2:$C$53,MATCH(N7,'State Premium Data'!$A$2:$A$53,0)),"") -> 80114 | Q7: =IFERROR(K7/O7,"") -> 0.26745452 | R7: =IFERROR(I7-P7,"") -> 29952 | S7: =IFERROR(R7/P7,"") -> 0.37386724
A8: Northeastern University | B8: MA | C8: Boston | D8: 5.2 | E8: 1497 | F8: 17326 | G8: 66162 | H8: 66162 | I8: 92538 | J8: 90.5 | K8: 24250 | L8: 0 | M8: No | N8: =INDEX('State Mapping'!$B$2:$B$53,MATCH(B8,'State Mapping'!$A$2:$A$53,0)) -> Massachusetts | O8: =IFERROR(INDEX('State Premium Data'!$D$2:$D$53,MATCH(N8,'State Premium Data'!$A$2:$A$53,0)),"") -> 36224 | P8: =IFERROR(INDEX('State Premium Data'!$C$2:$C$53,MATCH(N8,'State Premium Data'!$A$2:$A$53,0)),"") -> 79985 | Q8: =IFERROR(K8/O8,"") -> 0.66944567 | R8: =IFERROR(I8-P8,"") -> 12553 | S8: =IFERROR(R8/P8,"") -> 0.15694193
A9: Brown University | B9: RI | C9: Providence | D9: 5.4 | E9: 1546 | F9: 7226 | G9: 71412 | H9: 71412 | I9: 93487 | J9: 95.7 | K9: 11428 | L9: 3 | M9: No | N9: =INDEX('State Mapping'!$B$2:$B$53,MATCH(B9,'State Mapping'!$A$2:$A$53,0)) -> Rhode Island | O9: =IFERROR(INDEX('State Premium Data'!$D$2:$D$53,MATCH(N9,'State Premium Data'!$A$2:$A$53,0)),"") -> 24927 | P9: =IFERROR(INDEX('State Premium Data'!$C$2:$C$53,MATCH(N9,'State Premium Data'!$A$2:$A$53,0)),"") -> 68084 | Q9: =IFERROR(K9/O9,"") -> 0.4584587 | R9: =IFERROR(I9-P9,"") -> 25403 | S9: =IFERROR(R9/P9,"") -> 0.37311263
A10: University of Pennsylvania | B10: PA | C10: Philadelphia | D10: 5.4 | E10: 1553 | F10: 10650 | G10: 68686 | H10: 68686 | I10: 111371 | J10: 96.7 | K10: 15715 | L10: 5 | M10: Yes | N10: =INDEX('State Mapping'!$B$2:$B$53,MATCH(B10,'State Mapping'!$A$2:$A$53,0)) -> Pennsylvania | O10: =IFERROR(INDEX('State Premium Data'!$D$2:$D$53,MATCH(N10,'State Premium Data'!$A$2:$A$53,0)),"") -> 25342 | P10: =IFERROR(INDEX('State Premium Data'!$C$2:$C$53,MATCH(N10,'State Premium Data'!$A$2:$A$53,0)),"") -> 65678 | Q10: =IFERROR(K10/O10,"") -> 0.6201168 | R10: =IFERROR(I10-P10,"") -> 45693 | S10: =IFERROR(R10/P10,"") -> 0.69571242
A11: Duke University | B11: NC | C11: Durham | D11: 5.7 | E11: 1548 | F11: 6442 | G11: 68758 | H11: 68758 | I11: 97800 | J11: 96.3 | K11: 13000 | L11: 0 | M11: Yes | N11: =INDEX('State Mapping'!$B$2:$B$53,MATCH(B11,'State Mapping'!$A$2:$A$53,0)) -> North Carolina | O11: =IFERROR(INDEX('State Premium Data'!$D$2:$D$53,MATCH(N11,'State Premium Data'!$A$2:$A$53,0)),"") -> 25615 | P11: =IFERROR(INDEX('State Premium Data'!$C$2:$C$53,MATCH(N11,'State Premium Data'!$A$2:$A$53,0)),"") -> 62338 | Q11: =IFERROR(K11/O11,"") -> 0.50751513 | R11: =IFERROR(I11-P11,"") -> 35462 | S11: =IFERROR(R11/P11,"") -> 0.5688665
A12: Vanderbilt University | B12: TN | C12: Nashville | D12: 5.9 | E12: 1549 | F12: 7208 | G12: 67498 | H12: 67498 | I12: 91565 | J12: 93.1 | K12: 14000 | L12: 1 | M12: Yes | N12: =INDEX('State Mapping'!$B$2:$B$53,MATCH(B12,'State Mapping'!$A$2:$A$53,0)) -> Tennessee | O12: =IFERROR(INDEX('State Premium Data'!$D$2:$D$53,MATCH(N12,'State Premium Data'!$A$2:$A$53,0)),"") -> 23496 | P12: =IFERROR(INDEX('State Premium Data'!$C$2:$C$53,MATCH(N12,'State Premium Data'!$A$2:$A$53,0)),"") -> 61189 | Q12: =IFERROR(K12/O12,"") -> 0.5958461 | R12: =IFERROR(I12-P12,"") -> 30376 | S12: =IFERROR(R12/P12,"") -> 0.4964291
A13: Johns Hopkins University | B13: MD | C13: Baltimore | D13: 6.4 | E13: 1553 | F13: 5693 | G13: 65230 | H13: 65230 | I13: 87555 | J13: 94.2 | K13: 10250 | L13: 2 | M13: No | N13: =INDEX('State Mapping'!$B$2:$B$53,MATCH(B13,'State Mapping'!$A$2:$A$53,0)) -> Maryland | O13: =IFERROR(INDEX('State Premium Data'!$D$2:$D$53,MATCH(N13,'State Premium Data'!$A$2:$A$53,0)),"") -> 33970 | P13: =IFERROR(INDEX('State Premium Data'!$C$2:$C$53,MATCH(N13,'State Premium Data'!$A$2:$A$53,0)),"") -> 76748 | Q13: =IFERROR(K13/O13,"") -> 0.30173683 | R13: =IFERROR(I13-P13,"") -> 10807 | S13: =IFERROR(R13/P13,"") -> 0.14081149
... A15: Cornell University | B15: NY | C15: Ithaca | D15: 8.8 | E15: 1535 | F15: 15995 | G15: 69314 | H15: 69314 | I15: 104043 | J15: 95.3 | K15: 14000 | L15: 8 | M15: No | N15: =INDEX('State Mapping'!$B$2:$B$53,MATCH(B15,'State Mapping'!$A$2:$A$53,0)) -> New York | O15: =IFERROR(INDEX('State Premium Data'!$D$2:$D$53,MATCH(N15,'State Premium Data'!$A$2:$A$53,0)),"") -> 34733 | P15: =IFERROR(INDEX('State Premium Data'!$C$2:$C$53,MATCH(N15,'State Premium Data'!$A$2:$A$53,0)),"") -> 74504 | Q15: =IFERROR(K15/O15,"") -> 0.40307489 | R15: =IFERROR(I15-P15,"") -> 29539 | S15: =IFERROR(R15/P15,"") -> 0.39647536
A16: University of California-Los Angeles | B16: CA | C16: Los Angeles | D16: 9 | F16: 33475 | G16: 15203 | H16: 49403 | I16: 82511 | J16: 92.6 | K16: 14000 | L16: 43 | M16: Yes | N16: =INDEX('State Mapping'!$B$2:$B$53,MATCH(B16,'State Mapping'!$A$2:$A$53,0)) -> California | O16: =IFERROR(INDEX('State Premium Data'!$D$2:$D$53,MATCH(N16,'State Premium Data'!$A$2:$A$53,0)),"") -> 37475 | P16: =IFERROR(INDEX('State Premium Data'!$C$2:$C$53,MATCH(N16,'State Premium Data'!$A$2:$A$53,0)),"") -> 78278 | Q16: =IFERROR(K16/O16,"") -> 0.37358239 | R16: =IFERROR(I16-P16,"") -> 4233 | S16: =IFERROR(R16/P16,"") -> 0.054076497
A17: New York University | B17: NY | C17: New York | D17: 9.2 | E17: 1520 | F17: 28663 | G17: 62796 | H17: 62796 | I17: 82509 | J17: 88 | K17: 20500 | L17: 2 | M17: No | N17: =INDEX('State Mapping'!$B$2:$B$53,MATCH(B17,'State Mapping'!$A$2:$A$53,0)) -> New York | O17: =IFERROR(INDEX('State Premium Data'!$D$2:$D$53,MATCH(N17,'State Premium Data'!$A$2:$A$53,0)),"") -> 34733 | P17: =IFERROR(INDEX('State Premium Data'!$C$2:$C$53,MATCH(N17,'State Premium Data'!$A$2:$A$53,0)),"") -> 74504 | Q17: =IFERROR(K17/O17,"") -> 0.5902168 | R17: =IFERROR(I17-P17,"") -> 8005 | S17: =IFERROR(R17/P17,"") -> 0.1074439
A18: University of Southern California | B18: CA | C18: Los Angeles | D18: 9.8 | E18: 1495 | F18: 20443 | G18: 72097 | H18: 72097 | I18: 92498 | J18: 91.9 | K18: 18000 | L18: 2 | M18: No | N18: =INDEX('State Mapping'!$B$2:$B$53,MATCH(B18,'State Mapping'!$A$2:$A$53,0)) -> California | O18: =IFERROR(INDEX('State Premium Data'!$D$2:$D$53,MATCH(N18,'State Premium Data'!$A$2:$A$53,0)),"") -> 37475 | P18: =IFERROR(INDEX('State Premium Data'!$C$2:$C$53,MATCH(N18,'State Premium Data'!$A$2:$A$53,0)),"") -> 78278 | Q18: =IFERROR(K18/O18,"") -> 0.48032021 | R18: =IFERROR(I18-P18,"") -> 14220 | S18: =IFERROR(R18/P18,"") -> 0.18166024
A19: Emory University | B19: GA | C19: Atlanta | D19: 10.7 | E19: 1520 | F19: 7298 | G19: 64280 | H19: 64280 | I19: 80137 | J19: 91.4 | K19: 18250 | L19: 0 | M19: No | N19: =INDEX('State Mapping'!$B$2:$B$53,MATCH(B19,'State Mapping'!$A$2:$A$53,0)) -> Georgia | O19: =IFERROR(INDEX('State Premium Data'!$D$2:$D$53,MATCH(N19,'State Premium Data'!$A$2:$A$53,0)),"") -> 27365 | P19: =IFERROR(INDEX('State Premium Data'!$C$2:$C$53,MATCH(N19,'State Premium Data'!$A$2:$A$53,0)),"") -> 64185 | Q19: =IFERROR(K19/O19,"") -> 0.66691029 | R19: =IFERROR(I19-P19,"") -> 15952 | S19: =IFERROR(R19/P19,"") -> 0.24853159
A20: University of California-Berkeley | B20: CA | C20: Berkeley | D20: 11 | F20: 33068 | G20: 16347 | H20: 50547 | I20: 92446 | J20: 92.9 | K20: 13000 | L20: 43 | M20: Yes | N20: =INDEX('State Mapping'!$B$2:$B$53,MATCH(B20,'State Mapping'!$A$2:$A$53,0)) -> California | O20: =IFERROR(INDEX('State Premium Data'!$D$2:$D$53,MATCH(N20,'State Premium Data'!$A$2:$A$53,0)),"") -> 37475 | P20: =IFERROR(INDEX('State Premium Data'!$C$2:$C$53,MATCH(N20,'State Premium Data'!$A$2:$A$53,0)),"") -> 78278 | Q20: =IFERROR(K20/O20,"") -> 0.34689793 | R20: =IFERROR(I20-P20,"") -> 14168 | S20: =IFERROR(R20/P20,"") -> 0.18099594
A21: Boston University | B21: MA | C21: Boston | D21: 11.1 | E21: 1480 | F21: 18248 | G21: 68102 | H21: 68102 | I21: 83238 | J21: 89.3 | K21: 23250 | L21: 0 | M21: No | N21: =INDEX('State Mapping'!$B$2:$B$53,MATCH(B21,'State Mapping'!$A$2:$A$53,0)) -> Massachusetts | O21: =IFERROR(INDEX('State Premium Data'!$D$2:$D$53,MATCH(N21,'State Premium Data'!$A$2:$A$53,0)),"") -> 36224 | P21: =IFERROR(INDEX('State Premium Data'!$C$2:$C$53,MATCH(N21,'State Premium Data'!$A$2:$A$53,0)),"") -> 79985 | Q21: =IFERROR(K21/O21,"") -> 0.64183966 | R21: =IFERROR(I21-P21,"") -> 3253 | S21: =IFERROR(R21/P21,"") -> 0.040670126
A22: University of Notre Dame | B22: IN | C22: Notre Dame | D22: 11.3 | E22: 1520 | F22: 8818 | G22: 65025 | H22: 65025 | I22: 99980 | J22: 96 | K22: 19000 | L22: 0 | M22: No | N22: =INDEX('State Mapping'!$B$2:$B$53,MATCH(B22,'State Mapping'!$A$2:$A$53,0)) -> Indiana | O22: =IFERROR(INDEX('State Premium Data'!$D$2:$D$53,MATCH(N22,'State Premium Data'!$A$2:$A$53,0)),"") -> 21077 | P22: =IFERROR(INDEX('State Premium Data'!$C$2:$C$53,MATCH(N22,'State Premium Data'!$A$2:$A$53,0)),"") -> 60573 | Q22: =IFERROR(K22/O22,"") -> 0.90145656 | R22: =IFERROR(I22-P22,"") -> 39407 | S22: =IFERROR(R22/P22,"") -> 0.65057039
A23: Tufts University | B23: MA | C23: Medford | D23: 11.5 | E23: 1513 | F23: 7061 | G23: 70704 | H23: 70704 | I23: 83214 | J23: 93.4 | K23: 16250 | L23: 1 | M23: No | N23: =INDEX('State Mapping'!$B$2:$B$53,MATCH(B23,'State Mapping'!$A$2:$A$53,0)) -> Massachusetts | O23: =IFERROR(INDEX('State Premium Data'!$D$2:$D$53,MATCH(N23,'State Premium Data'!$A$2:$A$53,0)),"") -> 36224 | P23: =IFERROR(INDEX('State Premium Data'!$C$2:$C$53,MATCH(N23,'State Premium Data'!$A$2:$A$53,0)),"") -> 79985 | Q23: =IFERROR(K23/O23,"") -> 0.44859761 | R23: =IFERROR(I23-P23,"") -> 3229 | S23: =IFERROR(R23/P23,"") -> 0.040370069
A24: Carnegie Mellon University | B24: PA | C24: Pittsburgh | D24: 11.7 | E24: 1546 | F24: 7304 | G24: 66246 | H24: 66246 | I24: 114862 | J24: 93.3 | K24: 21750 | L24: 2 | M24: No | N24: =INDEX('State Mapping'!$B$2:$B$53,MATCH(B24,'State Mapping'!$A$2:$A$53,0)) -> Pennsylvania | O24: =IFERROR(INDEX('State Premium Data'!$D$2:$D$53,MATCH(N24,'State Premium Data'!$A$2:$A$53,0)),"") -> 25342 | P24: =IFERROR(INDEX('State Premium Data'!$C$2:$C$53,MATCH(N24,'State Premium Data'!$A$2:$A$53,0)),"") -> 65678 | Q24: =IFERROR(K24/O24,"") -> 0.85825902 | R24: =IFERROR(I24-P24,"") -> 49184 | S24: =IFERROR(R24/P24,"") -> 0.74886568
A25: Washington University in St Louis | B25: MO | C25: St. Louis | D25: 12.1 | E25: 1530 | F25: 7857 | G25: 65790 | H25: 65790 | I25: 86182 | J25: 94.3 | K25: 17500 | L25: 5 | M25: No | N25: =INDEX('State Mapping'!$B$2:$B$53,MATCH(B25,'State Mapping'!$A$2:$A$53,0)) -> Missouri | O25: =IFERROR(INDEX('State Premium Data'!$D$2:$D$53,MATCH(N25,'State Premium Data'!$A$2:$A$53,0)),"") -> 23998 | P25: =IFERROR(INDEX('State Premium Data'!$C$2:$C$53,MATCH(N25,'State Premium Data'!$A$2:$A$53,0)),"") -> 61418 | Q25: =IFERROR(K25/O25,"") -> 0.72922744 | R25: =IFERROR(I25-P25,"") -> 24764 | S25: =IFERROR(R25/P25,"") -> 0.40320427
A26: Georgetown University | B26: DC | C26: Washington | D26: 12.9 | E26: 1487 | F26: 7569 | G26: 68017 | H26: 68017 | I26: 103494 | J26: 94.5 | K26: 15500 | L26: 0 | M26: No | N26: =INDEX('State Mapping'!$B$2:$B$53,MATCH(B26,'State Mapping'!$A$2:$A$53,0)) -> District of Columbia | O26: =IFERROR(INDEX('State Premium Data'!$D$2:$D$53,MATCH(N26,'State Premium Data'!$A$2:$A$53,0)),"") -> 54913 | P26: =IFERROR(INDEX('State Premium Data'!$C$2:$C$53,MATCH(N26,'State Premium Data'!$A$2:$A$53,0)),"") -> 95628 | Q26: =IFERROR(K26/O26,"") -> 0.28226467 | R26: =IFERROR(I26-P26,"") -> 7866 | S26: =IFERROR(R26/P26,"") -> 0.082256243
A27: Tulane University of Louisiana | B27: LA | C27: New Orleans | D27: 14 | E27: 1448 | F27: 7767 | G27: 68678 | H27: 68678 | I27: 63268 | J27: 87.5 | K27: 20500 | L27: 0 | M27: No | N27: =INDEX('State Mapping'!$B$2:$B$53,MATCH(B27,'State Mapping'!$A$2:$A$53,0)) -> Louisiana | O27: =IFERROR(INDEX('State Premium Data'!$D$2:$D$53,MATCH(N27,'State Premium Data'!$A$2:$A$53,0)),"") -> 20975 | P27: =IFERROR(INDEX('State Premium Data'!$C$2:$C$53,MATCH(N27,'State Premium Data'!$A$2:$A$53,0)),"") -> 57107 | Q27: =IFERROR(K27/O27,"") -> 0.97735399 | R27: =IFERROR(I27-P27,"") -> 6161 | S27: =IFERROR(R27/P27,"") -> 0.1078852
A28: Georgia Institute of Technology-Main Campus | B28: GA | C28: Atlanta | D28: 14.1 | E28: 1480 | F28: 18785 | G28: 12058 | H28: 34484 | I28: 102772 | J28: 93.2 | K28: 21672 | L28: 0 | M28: No | N28: =INDEX('State Mapping'!$B$2:$B$53,MATCH(B28,'State Mapping'!$A$2:$A$53,0)) -> Georgia | O28: =IFERROR(INDEX('State Premium Data'!$D$2:$D$53,MATCH(N28,'State Premium Data'!$A$2:$A$53,0)),"") -> 27365 | P28: =IFERROR(INDEX('State Premium Data'!$C$2:$C$53,MATCH(N28,'State Premium Data'!$A$2:$A$53,0)),"") -> 64185 | Q28: =IFERROR(K28/O28,"") -> 0.79196053 | R28: =IFERROR(I28-P28,"") -> 38587 | S28: =IFERROR(R28/P28,"") -> 0.60118408
A29: University of North Carolina at Chapel Hill | B29: NC | C29: Chapel Hill | D29: 15.3 | E29: 1439 | F29: 20752 | G29: 8994 | H29: 41203 | I29: 72200 | J29: 91.6 | K29: 14000 | L29: 2 | M29: Yes | N29: =INDEX('State Mapping'!$B$2:$B$53,MATCH(B29,'State Mapping'!$A$2:$A$53,0)) -> North Carolina | O29: =IFERROR(INDEX('State Premium Data'!$D$2:$D$53,MATCH(N29,'State Premium Data'!$A$2:$A$53,0)),"") -> 25615 | P29: =IFERROR(INDEX('State Premium Data'!$C$2:$C$53,MATCH(N29,'State Premium Data'!$A$2:$A$53,0)),"") -> 62338 | Q29: =IFERROR(K29/O29,"") -> 0.54655475 | R29: =IFERROR(I29-P29,"") -> 9862 | S29: =IFERROR(R29/P29,"") -> 0.15820206
A30: University of Michigan-Ann Arbor | B30: MI | C30: Ann Arbor | D30: 15.6 | E30: 1465 | F30: 34177 | G30: 17736 | H30: 60946 | I30: 83648 | J30: 93.2 | K30: 19500 | L30: 1 | M30: Yes | N30: =INDEX('State Mapping'!$B$2:$B$53,MATCH(B30,'State Mapping'!$A$2:$A$53,0)) -> Michigan | O30: =IFERROR(INDEX('State Premium Data'!$D$2:$D$53,MATCH(N30,'State Premium Data'!$A$2:$A$53,0)),"") -> 27987 | P30: =IFERROR(INDEX('State Premium Data'!$C$2:$C$53,MATCH(N30,'State Premium Data'!$A$2:$A$53,0)),"") -> 64810 | Q30: =IFERROR(K30/O30,"") -> 0.69675206 | R30: =IFERROR(I30-P30,"") -> 18838 | S30: =IFERROR(R30/P30,"") -> 0.29066502
A31: Boston College | B31: MA | C31: Chestnut Hill | D31: 16.4 | E31: 1507 | F31: 10085 | G31: 70702 | H31: 70702 | I31: 103937 | J31: 90.9 | K31: 19000 | L31: 0 | M31: No | N31: =INDEX('State Mapping'!$B$2:$B$53,MATCH(B31,'State Mapping'!$A$2:$A$53,0)) -> Massachusetts | O31: =IFERROR(INDEX('State Premium Data'!$D$2:$D$53,MATCH(N31,'State Premium Data'!$A$2:$A$53,0)),"") -> 36224 | P31: =IFERROR(INDEX('State Premium Data'!$C$2:$C$53,MATCH(N31,'State Premium Data'!$A$2:$A$53,0)),"") -> 79985 | Q31: =IFERROR(K31/O31,"") -> 0.52451413 | R31: =IFERROR(I31-P31,"") -> 23952 | S31: =IFERROR(R31/P31,"") -> 0.29945615
A32: University of Virginia-Main Campus | B32: VA | C32: Charlottesville | D32: 16.8 | E32: 1480 | F32: 17597 | G32: 21803 | H32: 59512 | I32: 86863 | J32: 95.5 | K32: 17500 | L32: 0 | M32: Yes | N32: =INDEX('State Mapping'!$B$2:$B$53,MATCH(B32,'State Mapping'!$A$2:$A$53,0)) -> Virginia | O32: =IFERROR(INDEX('State Premium Data'!$D$2:$D$53,MATCH(N32,'State Premium Data'!$A$2:$A$53,0)),"") -> 33407 | P32: =IFERROR(INDEX('State Premium Data'!$C$2:$C$53,MATCH(N32,'State Premium Data'!$A$2:$A$53,0)),"") -> 74468 | Q32: =IFERROR(K32/O32,"") -> 0.52384231 | R32: =IFERROR(I32-P32,"") -> 12395 | S32: =IFERROR(R32/P32,"") -> 0.16644733
... A39: The University of Texas at Austin | B39: TX | C39: Austin | D39: 26.6 | E39: 1395 | F39: 42855 | G39: 11688 | H39: 44908 | I39: 75121 | J39: 88.3 | K39: 20500 | L39: 0 | M39: Yes | N39: =INDEX('State Mapping'!$B$2:$B$53,MATCH(B39,'State Mapping'!$A$2:$A$53,0)) -> Texas | O39: =IFERROR(INDEX('State Premium Data'!$D$2:$D$53,MATCH(N39,'State Premium Data'!$A$2:$A$53,0)),"") -> 29388 | P39: =IFERROR(INDEX('State Premium Data'!$C$2:$C$53,MATCH(N39,'State Premium Data'!$A$2:$A$53,0)),"") -> 66474 | Q39: =IFERROR(K39/O39,"") -> 0.69756363 | R39: =IFERROR(I39-P39,"") -> 8647 | S39: =IFERROR(R39/P39,"") -> 0.13008093
A40: University of California-San Diego | B40: CA | C40: La Jolla | D40: 26.7 | F40: 34948 | G40: 16758 | H40: 50958 | I40: 84943 | J40: 86.8 | K40: 15500 | L40: 43 | M40: Yes | N40: =INDEX('State Mapping'!$B$2:$B$53,MATCH(B40,'State Mapping'!$A$2:$A$53,0)) -> California | O40: =IFERROR(INDEX('State Premium Data'!$D$2:$D$53,MATCH(N40,'State Premium Data'!$A$2:$A$53,0)),"") -> 37475 | P40: =IFERROR(INDEX('State Premium Data'!$C$2:$C$53,MATCH(N40,'State Premium Data'!$A$2:$A$53,0)),"") -> 78278 | Q40: =IFERROR(K40/O40,"") -> 0.41360907 | R40: =IFERROR(I40-P40,"") -> 6665 | S40: =IFERROR(R40/P40,"") -> 0.085145252
A41: Villanova University | B41: PA | C41: Villanova | D41: 27 | E41: 1460 | F41: 6938 | G41: 67776 | H41: 67776 | I41: 100423 | J41: 92.1 | K41: 25874 | L41: 0 | M41: Yes | N41: =INDEX('State Mapping'!$B$2:$B$53,MATCH(B41,'State Mapping'!$A$2:$A$53,0)) -> Pennsylvania | O41: =IFERROR(INDEX('State Premium Data'!$D$2:$D$53,MATCH(N41,'State Premium Data'!$A$2:$A$53,0)),"") -> 25342 | P41: =IFERROR(INDEX('State Premium Data'!$C$2:$C$53,MATCH(N41,'State Premium Data'!$A$2:$A$53,0)),"") -> 65678 | Q41: =IFERROR(K41/O41,"") -> 1.0209928 | R41: =IFERROR(I41-P41,"") -> 34745 | S41: =IFERROR(R41/P41,"") -> 0.52902037
A42: University of California-Irvine | B42: CA | C42: Irvine | D42: 28.6 | F42: 30197 | G42: 15722 | H42: 49922 | I42: 80735 | J42: 86.4 | K42: 15000 | L42: 43 | M42: Yes | N42: =INDEX('State Mapping'!$B$2:$B$53,MATCH(B42,'State Mapping'!$A$2:$A$53,0)) -> California | O42: =IFERROR(INDEX('State Premium Data'!$D$2:$D$53,MATCH(N42,'State Premium Data'!$A$2:$A$53,0)),"") -> 37475 | P42: =IFERROR(INDEX('State Premium Data'!$C$2:$C$53,MATCH(N42,'State Premium Data'!$A$2:$A$53,0)),"") -> 78278 | Q42: =IFERROR(K42/O42,"") -> 0.40026684 | R42: =IFERROR(I42-P42,"") -> 2457 | S42: =IFERROR(R42/P42,"") -> 0.031388129
A43: California Polytechnic State University-San Luis Obispo | B43: CA | C43: San Luis Obispo | D43: 31.3 | F43: 21996 | G43: 13596 | H43: 34665 | I43: 90768 | J43: 85.7 | K43: 18500 | L43: 0 | M43: No | N43: =INDEX('State Mapping'!$B$2:$B$53,MATCH(B43,'State Mapping'!$A$2:$A$53,0)) -> California | O43: =IFERROR(INDEX('State Premium Data'!$D$2:$D$53,MATCH(N43,'State Premium Data'!$A$2:$A$53,0)),"") -> 37475 | P43: =IFERROR(INDEX('State Premium Data'!$C$2:$C$53,MATCH(N43,'State Premium Data'!$A$2:$A$53,0)),"") -> 78278 | Q43: =IFERROR(K43/O43,"") -> 0.49366244 | R43: =IFERROR(I43-P43,"") -> 12490 | S43: =IFERROR(R43/P43,"") -> 0.15955952
A44: University of California-Santa Barbara | B44: CA | C44: Santa Barbara | D44: 33 | F44: 23113 | G44: 16414 | H44: 50614 | I44: 74915 | J44: 84.2 | K44: 13993 | L44: 43 | M44: Yes | N44: =INDEX('State Mapping'!$B$2:$B$53,MATCH(B44,'State Mapping'!$A$2:$A$53,0)) -> California | O44: =IFERROR(INDEX('State Premium Data'!$D$2:$D$53,MATCH(N44,'State Premium Data'!$A$2:$A$53,0)),"") -> 37475 | P44: =IFERROR(INDEX('State Premium Data'!$C$2:$C$53,MATCH(N44,'State Premium Data'!$A$2:$A$53,0)),"") -> 78278 | Q44: =IFERROR(K44/O44,"") -> 0.3733956 | R44: =IFERROR(I44-P44,"") -> -3363 | S44: =IFERROR(R44/P44,"") -> -0.042962263
A45: Fairfield University | B45: CT | C45: Fairfield | D45: 33.3 | E45: 1335 | F45: 5373 | G45: 58350 | H45: 58350 | I45: 88794 | J45: 84.1 | K45: 26000 | L45: 0 | M45: No | N45: =INDEX('State Mapping'!$B$2:$B$53,MATCH(B45,'State Mapping'!$A$2:$A$53,0)) -> Connecticut | O45: =IFERROR(INDEX('State Premium Data'!$D$2:$D$53,MATCH(N45,'State Premium Data'!$A$2:$A$53,0)),"") -> 33855 | P45: =IFERROR(INDEX('State Premium Data'!$C$2:$C$53,MATCH(N45,'State Premium Data'!$A$2:$A$53,0)),"") -> 75975 | Q45: =IFERROR(K45/O45,"") -> 0.7679811 | R45: =IFERROR(I45-P45,"") -> 12819 | S45: =IFERROR(R45/P45,"") -> 0.16872655
A46: William & Mary | B46: VA | C46: Williamsburg | D46: 34.1 | E46: 1473 | F46: 7055 | G46: 25914 | H46: 51038 | I46: 73490 | J46: 90.2 | K46: 18500 | L46: 0 | M46: No | N46: =INDEX('State Mapping'!$B$2:$B$53,MATCH(B46,'State Mapping'!$A$2:$A$53,0)) -> Virginia | O46: =IFERROR(INDEX('State Premium Data'!$D$2:$D$53,MATCH(N46,'State Premium Data'!$A$2:$A$53,0)),"") -> 33407 | P46: =IFERROR(INDEX('State Premium Data'!$C$2:$C$53,MATCH(N46,'State Premium Data'!$A$2:$A$53,0)),"") -> 74468 | Q46: =IFERROR(K46/O46,"") -> 0.55377615 | R46: =IFERROR(I46-P46,"") -> -978 | S46: =IFERROR(R46/P46,"") -> -0.013133158
A47: Southern University and A & M College | B47: LA | C47: Baton Rouge | D47: 35.1 | E47: 942 | F47: 5519 | G47: 9922 | H47: 17272 | I47: 43371 | J47: 27.7 | K47: 29251 | L47: 0 | M47: No | N47: =INDEX('State Mapping'!$B$2:$B$53,MATCH(B47,'State Mapping'!$A$2:$A$53,0)) -> Louisiana | O47: =IFERROR(INDEX('State Premium Data'!$D$2:$D$53,MATCH(N47,'State Premium Data'!$A$2:$A$53,0)),"") -> 20975 | P47: =IFERROR(INDEX('State Premium Data'!$C$2:$C$53,MATCH(N47,'State Premium Data'!$A$2:$A$53,0)),"") -> 57107 | Q47: =IFERROR(K47/O47,"") -> 1.394565 | R47: =IFERROR(I47-P47,"") -> -13736 | S47: =IFERROR(R47/P47,"") -> -0.24053093
A48: San Diego State University | B48: CA | C48: San Diego | D48: 36.2 | F48: 35377 | G48: 8728 | H48: 21328 | I48: 64909 | J48: 77.3 | K48: 15000 | L48: 0 | M48: No | N48: =INDEX('State Mapping'!$B$2:$B$53,MATCH(B48,'State Mapping'!$A$2:$A$53,0)) -> California | O48: =IFERROR(INDEX('State Premium Data'!$D$2:$D$53,MATCH(N48,'State Premium Data'!$A$2:$A$53,0)),"") -> 37475 | P48: =IFERROR(INDEX('State Premium Data'!$C$2:$C$53,MATCH(N48,'State Premium Data'!$A$2:$A$53,0)),"") -> 78278 | Q48: =IFERROR(K48/O48,"") -> 0.40026684 | R48: =IFERROR(I48-P48,"") -> -13369 | S48: =IFERROR(R48/P48,"") -> -0.17078873
A49: Case Western Reserve University | B49: OH | C49: Cleveland | D49: 36.5 | E49: 1513 | F49: 6437 | G49: 66608 | H49: 66608 | I49: 87989 | J49: 87.1 | K49: 24000 | L49: 0 | M49: No | N49: =INDEX('State Mapping'!$B$2:$B$53,MATCH(B49,'State Mapping'!$A$2:$A$53,0)) -> Ohio | O49: =IFERROR(INDEX('State Premium Data'!$D$2:$D$53,MATCH(N49,'State Premium Data'!$A$2:$A$53,0)),"") -> 26943 | P49: =IFERROR(INDEX('State Premium Data'!$C$2:$C$53,MATCH(N49,'State Premium Data'!$A$2:$A$53,0)),"") -> 64933 | Q49: =IFERROR(K49/O49,"") -> 0.8907694 | R49: =IFERROR(I49-P49,"") -> 23056 | S49: =IFERROR(R49/P49,"") -> 0.35507369
A50: University of Georgia | B50: GA | C50: Athens | D50: 37.7 | E50: 1397 | F50: 32137 | G50: 11450 | H50: 31688 | I50: 68726 | J50: 88.9 | K50: 18500 | L50: 0 | M50: Yes | N50: =INDEX('State Mapping'!$B$2:$B$53,MATCH(B50,'State Mapping'!$A$2:$A$53,0)) -> Georgia | O50: =IFERROR(INDEX('State Premium Data'!$D$2:$D$53,MATCH(N50,'State Premium Data'!$A$2:$A$53,0)),"") -> 27365 | P50: =IFERROR(INDEX('State Premium Data'!$C$2:$C$53,MATCH(N50,'State Premium Data'!$A$2:$A$53,0)),"") -> 64185 | Q50: =IFERROR(K50/O50,"") -> 0.67604604 | R50: =IFERROR(I50-P50,"") -> 4541 | S50: =IFERROR(R50/P50,"") -> 0.070748617
A51: Clemson University | B51: SC | C51: Clemson | D51: 38.3 | E51: 1353 | F51: 23300 | G51: 15554 | H51: 40866 | I51: 71513 | J51: 87.2 | K51: 21500 | L51: 0 | M51: Yes | N51: =INDEX('State Mapping'!$B$2:$B$53,MATCH(B51,'State Mapping'!$A$2:$A$53,0)) -> South Carolina | O51: =IFERROR(INDEX('State Premium Data'!$D$2:$D$53,MATCH(N51,'State Premium Data'!$A$2:$A$53,0)),"") -> 23850 | P51: =IFERROR(INDEX('State Premium Data'!$C$2:$C$53,MATCH(N51,'State Premium Data'!$A$2:$A$53,0)),"") -> 60590 | Q51: =IFERROR(K51/O51,"") -> 0.90146751 | R51: =IFERROR(I51-P51,"") -> 10923 | S51: =IFERROR(R51/P51,"") -> 0.18027727
A52: Binghamton University | B52: NY | C52: Vestal | D52: 38.6 | E52: 1415 | F52: 14655 | G52: 10567 | H52: 30447 | I52: 80596 | J52: 82.6 | K52: 18500 | L52: 0 | M52: No | N52: =INDEX('State Mapping'!$B$2:$B$53,MATCH(B52,'State Mapping'!$A$2:$A$53,0)) -> New York | O52: =IFERROR(INDEX('State Premium Data'!$D$2:$D$53,MATCH(N52,'State Premium Data'!$A$2:$A$53,0)),"") -> 34733 | P52: =IFERROR(INDEX('State Premium Data'!$C$2:$C$53,MATCH(N52,'State Premium Data'!$A$2:$A$53,0)),"") -> 74504 | Q52: =IFERROR(K52/O52,"") -> 0.53263467 | R52: =IFERROR(I52-P52,"") -> 6092 | S52: =IFERROR(R52/P52,"") -> 0.081767422
A53: University of Washington-Seattle Campus | B53: WA | C53: Seattle | D53: 39.1 | F53: 31942 | G53: 12973 | H53: 43209 | I53: 78466 | J53: 84.5 | K53: 14615 | L53: 0 | M53: No | N53: =INDEX('State Mapping'!$B$2:$B$53,MATCH(B53,'State Mapping'!$A$2:$A$53,0)) -> Washington | O53: =IFERROR(INDEX('State Premium Data'!$D$2:$D$53,MATCH(N53,'State Premium Data'!$A$2:$A$53,0)),"") -> 33619 | P53: =IFERROR(INDEX('State Premium Data'!$C$2:$C$53,MATCH(N53,'State Premium Data'!$A$2:$A$53,0)),"") -> 78485 | Q53: =IFERROR(K53/O53,"") -> 0.43472441 | R53: =IFERROR(I53-P53,"") -> -19 | S53: =IFERROR(R53/P53,"") -> -0.00024208447
A54: University of Rochester | B54: NY | C54: Rochester | D54: 40.1 | E54: 1488 | F54: 6331 | G54: 67080 | H54: 67080 | I54: 79042 | J54: 85 | K54: 21000 | L54: 1 | M54: No | N54: =INDEX('State Mapping'!$B$2:$B$53,MATCH(B54,'State Mapping'!$A$2:$A$53,0)) -> New York | O54: =IFERROR(INDEX('State Premium Data'!$D$2:$D$53,MATCH(N54,'State Premium Data'!$A$2:$A$53,0)),"") -> 34733 | P54: =IFERROR(INDEX('State Premium Data'!$C$2:$C$53,MATCH(N54,'State Premium Data'!$A$2:$A$53,0)),"") -> 74504 | Q54: =IFERROR(K54/O54,"") -> 0.60461233 | R54: =IFERROR(I54-P54,"") -> 4538 | S54: =IFERROR(R54/P54,"") -> 0.060909481
A55: University of Central Florida | B55: FL | C55: Orlando | D55: 40.1 | E55: 1269 | F55: 59146 | G55: 6368 | H55: 22467 | I55: 58308 | J55: 76.6 | K55: 18190 | L55: 0 | M55: Yes | N55: =INDEX('State Mapping'!$B$2:$B$53,MATCH(B55,'State Mapping'!$A$2:$A$53,0)) -> Florida | O55: =IFERROR(INDEX('State Premium Data'!$D$2:$D$53,MATCH(N55,'State Premium Data'!$A$2:$A$53,0)),"") -> 21625 | P55: =IFERROR(INDEX('State Premium Data'!$C$2:$C$53,MATCH(N55,'State Premium Data'!$A$2:$A$53,0)),"") -> 58009 | Q55: =IFERROR(K55/O55,"") -> 0.84115607 | R55: =IFERROR(I55-P55,"") -> 299 | S55: =IFERROR(R55/P55,"") -> 0.0051543726
A56: The University of Tampa | B56: FL | C56: Tampa | D56: 40.3 | F56: 10572 | G56: 34408 | H56: 34408 | I56: 59436 | J56: 62.8 | K56: 24211 | L56: 0 | M56: No | N56: =INDEX('State Mapping'!$B$2:$B$53,MATCH(B56,'State Mapping'!$A$2:$A$53,0)) -> Florida | O56: =IFERROR(INDEX('State Premium Data'!$D$2:$D$53,MATCH(N56,'State Premium Data'!$A$2:$A$53,0)),"") -> 21625 | P56: =IFERROR(INDEX('State Premium Data'!$C$2:$C$53,MATCH(N56,'State Premium Data'!$A$2:$A$53,0)),"") -> 58009 | Q56: =IFERROR(K56/O56,"") -> 1.1195838 | R56: =IFERROR(I56-P56,"") -> 1427 | S56: =IFERROR(R56/P56,"") -> 0.024599631
A57: Howard University | B57: DC | C57: Washington | D57: 41.3 | E57: 1213 | F57: 10108 | G57: 35810 | H57: 35810 | I57: 63066 | J57: 69.3 | K57: 24500 | L57: 0 | M57: Yes | N57: =INDEX('State Mapping'!$B$2:$B$53,MATCH(B57,'State Mapping'!$A$2:$A$53,0)) -> District of Columbia | O57: =IFERROR(INDEX('State Premium Data'!$D$2:$D$53,MATCH(N57,'State Premium Data'!$A$2:$A$53,0)),"") -> 54913 | P57: =IFERROR(INDEX('State Premium Data'!$C$2:$C$53,MATCH(N57,'State Premium Data'!$A$2:$A$53,0)),"") -> 95628 | Q57: =IFERROR(K57/O57,"") -> 0.44616029 | R57: =IFERROR(I57-P57,"") -> -32562 | S57: =IFERROR(R57/P57,"") -> -0.34050696
A58: The University of Tennessee-Knoxville | B58: TN | C58: Knoxville | D58: 41.6 | E58: 1311 | F58: 30418 | G58: 13812 | H58: 33256 | I58: 60249 | J58: 73.7 | K58: 20500 | L58: 0 | M58: Yes | N58: =INDEX('State Mapping'!$B$2:$B$53,MATCH(B58,'State Mapping'!$A$2:$A$53,0)) -> Tennessee | O58: =IFERROR(INDEX('State Premium Data'!$D$2:$D$53,MATCH(N58,'State Premium Data'!$A$2:$A$53,0)),"") -> 23496 | P58: =IFERROR(INDEX('State Premium Data'!$C$2:$C$53,MATCH(N58,'State Premium Data'!$A$2:$A$53,0)),"") -> 61189 | Q58: =IFERROR(K58/O58,"") -> 0.87248893 | R58: =IFERROR(I58-P58,"") -> -940 | S58: =IFERROR(R58/P58,"") -> -0.015362238
A59: North Carolina State University at Raleigh | B59: NC | C59: Raleigh | D59: 41.7 | E59: 1376 | F59: 27371 | G59: 8799 | H59: 32847 | I59: 68758 | J59: 84.7 | K59: 20121 | L59: 0 | M59: Yes | N59: =INDEX('State Mapping'!$B$2:$B$53,MATCH(B59,'State Mapping'!$A$2:$A$53,0)) -> North Carolina | O59: =IFERROR(INDEX('State Premium Data'!$D$2:$D$53,MATCH(N59,'State Premium Data'!$A$2:$A$53,0)),"") -> 25615 | P59: =IFERROR(INDEX('State Premium Data'!$C$2:$C$53,MATCH(N59,'State Premium Data'!$A$2:$A$53,0)),"") -> 62338 | Q59: =IFERROR(K59/O59,"") -> 0.7855163 | R59: =IFERROR(I59-P59,"") -> 6420 | S59: =IFERROR(R59/P59,"") -> 0.10298694
A60: University of California-Davis | B60: CA | C60: Davis | D60: 41.8 | F60: 32253 | G60: 16774 | H60: 50974 | I60: 80838 | J60: 85.4 | K60: 13000 | L60: 43 | M60: Yes | N60: =INDEX('State Mapping'!$B$2:$B$53,MATCH(B60,'State Mapping'!$A$2:$A$53,0)) -> California | O60: =IFERROR(INDEX('State Premium Data'!$D$2:$D$53,MATCH(N60,'State Premium Data'!$A$2:$A$53,0)),"") -> 37475 | P60: =IFERROR(INDEX('State Premium Data'!$C$2:$C$53,MATCH(N60,'State Premium Data'!$A$2:$A$53,0)),"") -> 78278 | Q60: =IFERROR(K60/O60,"") -> 0.34689793 | R60: =IFERROR(I60-P60,"") -> 2560 | S60: =IFERROR(R60/P60,"") -> 0.032703953
A61: University of Illinois Urbana-Champaign | B61: IL | C61: Champaign | D61: 42.4 | E61: 1440 | F61: 36258 | G61: 16004 | H61: 35124 | I61: 81054 | J61: 85 | K61: 19500 | L61: 4 | M61: Yes | N61: =INDEX('State Mapping'!$B$2:$B$53,MATCH(B61,'State Mapping'!$A$2:$A$53,0)) -> Illinois | O61: =IFERROR(INDEX('State Premium Data'!$D$2:$D$53,MATCH(N61,'State Premium Data'!$A$2:$A$53,0)),"") -> 30842 | P61: =IFERROR(INDEX('State Premium Data'!$C$2:$C$53,MATCH(N61,'State Premium Data'!$A$2:$A$53,0)),"") -> 71127 | Q61: =IFERROR(K61/O61,"") -> 0.63225472 | R61: =IFERROR(I61-P61,"") -> 9927 | S61: =IFERROR(R61/P61,"") -> 0.13956725
A62: University of South Florida | B62: FL | C62: Tampa | D62: 43.2 | E62: 1227 | F62: 37207 | G62: 6410 | H62: 17324 | I62: 57743 | J62: 75.7 | K62: 17988 | L62: 0 | M62: Yes | N62: =INDEX('State Mapping'!$B$2:$B$53,MATCH(B62,'State Mapping'!$A$2:$A$53,0)) -> Florida | O62: =IFERROR(INDEX('State Premium Data'!$D$2:$D$53,MATCH(N62,'State Premium Data'!$A$2:$A$53,0)),"") -> 21625 | P62: =IFERROR(INDEX('State Premium Data'!$C$2:$C$53,MATCH(N62,'State Premium Data'!$A$2:$A$53,0)),"") -> 58009 | Q62: =IFERROR(K62/O62,"") -> 0.83181503 | R62: =IFERROR(I62-P62,"") -> -266 | S62: =IFERROR(R62/P62,"") -> -0.0045854954
A63: Berklee College of Music | B63: MA | C63: Boston | D63: 43.5 | F63: 7468 | G63: 52040 | H63: 52040 | I63: 33647 | J63: 66.8 | K63: 25000 | L63: 0 | M63: No | N63: =INDEX('State Mapping'!$B$2:$B$53,MATCH(B63,'State Mapping'!$A$2:$A$53,0)) -> Massachusetts | O63: =IFERROR(INDEX('State Premium Data'!$D$2:$D$53,MATCH(N63,'State Premium Data'!$A$2:$A$53,0)),"") -> 36224 | P63: =IFERROR(INDEX('State Premium Data'!$C$2:$C$53,MATCH(N63,'State Premium Data'!$A$2:$A$53,0)),"") -> 79985 | Q63: =IFERROR(K63/O63,"") -> 0.69015018 | R63: =IFERROR(I63-P63,"") -> -46338 | S63: =IFERROR(R63/P63,"") -> -0.57933363
A64: Texas A & M International University | B64: TX | C64: Laredo | D64: 44.4 | E64: 993 | F64: 6667 | G64: 7894 | H64: 19454 | I64: 48386 | J64: 47.6 | K64: 15000 | L64: 0 | M64: No | N64: =INDEX('State Mapping'!$B$2:$B$53,MATCH(B64,'State Mapping'!$A$2:$A$53,0)) -> Texas | O64: =IFERROR(INDEX('State Premium Data'!$D$2:$D$53,MATCH(N64,'State Premium Data'!$A$2:$A$53,0)),"") -> 29388 | P64: =IFERROR(INDEX('State Premium Data'!$C$2:$C$53,MATCH(N64,'State Premium Data'!$A$2:$A$53,0)),"") -> 66474 | Q64: =IFERROR(K64/O64,"") -> 0.51041241 | R64: =IFERROR(I64-P64,"") -> -18088 | S64: =IFERROR(R64/P64,"") -> -0.27210639
A65: Texas Christian University | B65: TX | C65: Fort Worth | D65: 44.5 | E65: 1298 | F65: 11026 | G65: 61740 | H65: 61740 | I65: 68424 | J65: 85.6 | K65: 21500 | L65: 0 | M65: Yes | N65: =INDEX('State Mapping'!$B$2:$B$53,MATCH(B65,'State Mapping'!$A$2:$A$53,0)) -> Texas | O65: =IFERROR(INDEX('State Premium Data'!$D$2:$D$53,MATCH(N65,'State Premium Data'!$A$2:$A$53,0)),"") -> 29388 | P65: =IFERROR(INDEX('State Premium Data'!$C$2:$C$53,MATCH(N65,'State Premium Data'!$A$2:$A$53,0)),"") -> 66474 | Q65: =IFERROR(K65/O65,"") -> 0.73159113 | R65: =IFERROR(I65-P65,"") -> 1950 | S65: =IFERROR(R65/P65,"") -> 0.029334778
A66: University of Maryland-College Park | B66: MD | C66: College Park | D66: 44.8 | E66: 1473 | F66: 30760 | G66: 11809 | H66: 41186 | I66: 82860 | J66: 88.6 | K66: 19000 | L66: 0 | M66: No | N66: =INDEX('State Mapping'!$B$2:$B$53,MATCH(B66,'State Mapping'!$A$2:$A$53,0)) -> Maryland | O66: =IFERROR(INDEX('State Premium Data'!$D$2:$D$53,MATCH(N66,'State Premium Data'!$A$2:$A$53,0)),"") -> 33970 | P66: =IFERROR(INDEX('State Premium Data'!$C$2:$C$53,MATCH(N66,'State Premium Data'!$A$2:$A$53,0)),"") -> 76748 | Q66: =IFERROR(K66/O66,"") -> 0.55931704 | R66: =IFERROR(I66-P66,"") -> 6112 | S66: =IFERROR(R66/P66,"") -> 0.079637254
A67: Loyola Marymount University | B67: CA | C67: Los Angeles | D67: 45.1 | E67: 1359 | F67: 7094 | G67: 62357 | H67: 62357 | I67: 78349 | J67: 79.3 | K67: 19500 | L67: 0 | M67: No | N67: =INDEX('State Mapping'!$B$2:$B$53,MATCH(B67,'State Mapping'!$A$2:$A$53,0)) -> California | O67: =IFERROR(INDEX('State Premium Data'!$D$2:$D$53,MATCH(N67,'State Premium Data'!$A$2:$A$53,0)),"") -> 37475 | P67: =IFERROR(INDEX('State Premium Data'!$C$2:$C$53,MATCH(N67,'State Premium Data'!$A$2:$A$53,0)),"") -> 78278 | Q67: =IFERROR(K67/O67,"") -> 0.5203469 | R67: =IFERROR(I67-P67,"") -> 71 | S67: =IFERROR(R67/P67,"") -> 0.00090702368
A68: University of Wisconsin-Madison | B68: WI | C68: Madison | D68: 45.2 | E68: 1427 | F68: 36902 | G68: 11603 | H68: 42103 | I68: 73792 | J68: 89.4 | K68: 20484 | L68: 3 | M68: Yes | N68: =INDEX('State Mapping'!$B$2:$B$53,MATCH(B68,'State Mapping'!$A$2:$A$53,0)) -> Wisconsin | O68: =IFERROR(INDEX('State Premium Data'!$D$2:$D$53,MATCH(N68,'State Premium Data'!$A$2:$A$53,0)),"") -> 22716 | P68: =IFERROR(INDEX('State Premium Data'!$C$2:$C$53,MATCH(N68,'State Premium Data'!$A$2:$A$53,0)),"") -> 64320 | Q68: =IFERROR(K68/O68,"") -> 0.90174326 | R68: =IFERROR(I68-P68,"") -> 9472 | S68: =IFERROR(R68/P68,"") -> 0.14726368
A69: Auburn University | B69: AL | C69: Auburn | D69: 45.9 | E69: 1345 | F69: 26816 | G69: 12890 | H69: 34922 | I69: 65337 | J69: 80.6 | K69: 21000 | L69: 0 | M69: No | N69: =INDEX('State Mapping'!$B$2:$B$53,MATCH(B69,'State Mapping'!$A$2:$A$53,0)) -> Alabama | O69: =IFERROR(INDEX('State Premium Data'!$D$2:$D$53,MATCH(N69,'State Premium Data'!$A$2:$A$53,0)),"") -> 23541 | P69: =IFERROR(INDEX('State Premium Data'!$C$2:$C$53,MATCH(N69,'State Premium Data'!$A$2:$A$53,0)),"") -> 60156 | Q69: =IFERROR(K69/O69,"") -> 0.89206066 | R69: =IFERROR(I69-P69,"") -> 5181 | S69: =IFERROR(R69/P69,"") -> 0.086126072
A70: Syracuse University | B70: NY | C70: Syracuse | D70: 45.9 | E70: 1375 | F70: 15477 | G70: 65528 | H70: 65528 | I70: 79164 | J70: 82.5 | K70: 26000 | L70: 0 | M70: No | N70: =INDEX('State Mapping'!$B$2:$B$53,MATCH(B70,'State Mapping'!$A$2:$A$53,0)) -> New York | O70: =IFERROR(INDEX('State Premium Data'!$D$2:$D$53,MATCH(N70,'State Premium Data'!$A$2:$A$53,0)),"") -> 34733 | P70: =IFERROR(INDEX('State Premium Data'!$C$2:$C$53,MATCH(N70,'State Premium Data'!$A$2:$A$53,0)),"") -> 74504 | Q70: =IFERROR(K70/O70,"") -> 0.74856764 | R70: =IFERROR(I70-P70,"") -> 4660 | S70: =IFERROR(R70/P70,"") -> 0.062546977
A71: California State University-Long Beach | B71: CA | C71: Long Beach | D71: 46.3 | F71: 35924 | G71: 7350 | H71: 19950 | I71: 64403 | J71: 69.3 | K71: 14289 | L71: 0 | M71: No | N71: =INDEX('State Mapping'!$B$2:$B$53,MATCH(B71,'State Mapping'!$A$2:$A$53,0)) -> California | O71: =IFERROR(INDEX('State Premium Data'!$D$2:$D$53,MATCH(N71,'State Premium Data'!$A$2:$A$53,0)),"") -> 37475 | P71: =IFERROR(INDEX('State Premium Data'!$C$2:$C$53,MATCH(N71,'State Premium Data'!$A$2:$A$53,0)),"") -> 78278 | Q71: =IFERROR(K71/O71,"") -> 0.3812942 | R71: =IFERROR(I71-P71,"") -> -13875 | S71: =IFERROR(R71/P71,"") -> -0.17725287
A72: George Washington University | B72: DC | C72: Washington | D72: 47.1 | E72: 1433 | F72: 11182 | G72: 67710 | H72: 67710 | I72: 90873 | J72: 84.5 | K72: 20449 | L72: 0 | M72: No | N72: =INDEX('State Mapping'!$B$2:$B$53,MATCH(B72,'State Mapping'!$A$2:$A$53,0)) -> District of Columbia | O72: =IFERROR(INDEX('State Premium Data'!$D$2:$D$53,MATCH(N72,'State Premium Data'!$A$2:$A$53,0)),"") -> 54913 | P72: =IFERROR(INDEX('State Premium Data'!$C$2:$C$53,MATCH(N72,'State Premium Data'!$A$2:$A$53,0)),"") -> 95628 | Q72: =IFERROR(K72/O72,"") -> 0.37238905 | R72: =IFERROR(I72-P72,"") -> -4755 | S72: =IFERROR(R72/P72,"") -> -0.04972393
A73: CUNY Bernard M Baruch College | B73: NY | C73: New York | D73: 47.5 | E73: 1280 | F73: 16154 | G73: 7464 | H73: 15414 | I73: 75971 | J73: 72.1 | K73: 11512 | L73: 0 | M73: No | N73: =INDEX('State Mapping'!$B$2:$B$53,MATCH(B73,'State Mapping'!$A$2:$A$53,0)) -> New York | O73: =IFERROR(INDEX('State Premium Data'!$D$2:$D$53,MATCH(N73,'State Premium Data'!$A$2:$A$53,0)),"") -> 34733 | P73: =IFERROR(INDEX('State Premium Data'!$C$2:$C$53,MATCH(N73,'State Premium Data'!$A$2:$A$53,0)),"") -> 74504 | Q73: =IFERROR(K73/O73,"") -> 0.33144272 | R73: =IFERROR(I73-P73,"") -> 1467 | S73: =IFERROR(R73/P73,"") -> 0.019690218
A74: Santa Clara University | B74: CA | C74: Santa Clara | D74: 48 | E74: 1426 | F74: 6552 | G74: 61293 | H74: 61293 | I74: 109183 | J74: 88.2 | K74: 19162 | L74: 0 | M74: Yes | N74: =INDEX('State Mapping'!$B$2:$B$53,MATCH(B74,'State Mapping'!$A$2:$A$53,0)) -> California | O74: =IFERROR(INDEX('State Premium Data'!$D$2:$D$53,MATCH(N74,'State Premium Data'!$A$2:$A$53,0)),"") -> 37475 | P74: =IFERROR(INDEX('State Premium Data'!$C$2:$C$53,MATCH(N74,'State Premium Data'!$A$2:$A$53,0)),"") -> 78278 | Q74: =IFERROR(K74/O74,"") -> 0.51132755 | R74: =IFERROR(I74-P74,"") -> 30905 | S74: =IFERROR(R74/P74,"") -> 0.3948108
A75: Stony Brook University | B75: NY | C75: Stony Brook | D75: 49 | E75: 1419 | F75: 18101 | G75: 10931 | H75: 32741 | I75: 74502 | J75: 76.7 | K75: 18228 | L75: 0 | M75: No | N75: =INDEX('State Mapping'!$B$2:$B$53,MATCH(B75,'State Mapping'!$A$2:$A$53,0)) -> New York | O75: =IFERROR(INDEX('State Premium Data'!$D$2:$D$53,MATCH(N75,'State Premium Data'!$A$2:$A$53,0)),"") -> 34733 | P75: =IFERROR(INDEX('State Premium Data'!$C$2:$C$53,MATCH(N75,'State Premium Data'!$A$2:$A$53,0)),"") -> 74504 | Q75: =IFERROR(K75/O75,"") -> 0.5248035 | R75: =IFERROR(I75-P75,"") -> -2 | S75: =IFERROR(R75/P75,"") -> -2.6844196e-05
A76: Purdue University-Main Campus | B76: IN | C76: West Lafayette | D76: 49.9 | E76: 1364 | F76: 44503 | G76: 9992 | H76: 28794 | I76: 72424 | J76: 83.1 | K76: 19500 | L76: 2 | M76: Yes | N76: =INDEX('State Mapping'!$B$2:$B$53,MATCH(B76,'State Mapping'!$A$2:$A$53,0)) -> Indiana | O76: =IFERROR(INDEX('State Premium Data'!$D$2:$D$53,MATCH(N76,'State Premium Data'!$A$2:$A$53,0)),"") -> 21077 | P76: =IFERROR(INDEX('State Premium Data'!$C$2:$C$53,MATCH(N76,'State Premium Data'!$A$2:$A$53,0)),"") -> 60573 | Q76: =IFERROR(K76/O76,"") -> 0.92517911 | R76: =IFERROR(I76-P76,"") -> 11851 | S76: =IFERROR(R76/P76,"") -> 0.19564823
A77: North Carolina A & T State University | B77: NC | C77: Greensboro | D77: 49.9 | E77: 1074 | F77: 12182 | G77: 6813 | H77: 20673 | I77: 44440 | J77: 56.2 | K77: 27000 | L77: 0 | M77: No | N77: =INDEX('State Mapping'!$B$2:$B$53,MATCH(B77,'State Mapping'!$A$2:$A$53,0)) -> North Carolina | O77: =IFERROR(INDEX('State Premium Data'!$D$2:$D$53,MATCH(N77,'State Premium Data'!$A$2:$A$53,0)),"") -> 25615 | P77: =IFERROR(INDEX('State Premium Data'!$C$2:$C$53,MATCH(N77,'State Premium Data'!$A$2:$A$53,0)),"") -> 62338 | Q77: =IFERROR(K77/O77,"") -> 1.0540699 | R77: =IFERROR(I77-P77,"") -> -17898 | S77: =IFERROR(R77/P77,"") -> -0.28711219
A78: Baylor University | B78: TX | C78: Waco | D78: 51.3 | E78: 1329 | F78: 14785 | G78: 58100 | H78: 58100 | I78: 65793 | J78: 80.1 | K78: 23000 | L78: 0 | M78: No | N78: =INDEX('State Mapping'!$B$2:$B$53,MATCH(B78,'State Mapping'!$A$2:$A$53,0)) -> Texas | O78: =IFERROR(INDEX('State Premium Data'!$D$2:$D$53,MATCH(N78,'State Premium Data'!$A$2:$A$53,0)),"") -> 29388 | P78: =IFERROR(INDEX('State Premium Data'!$C$2:$C$53,MATCH(N78,'State Premium Data'!$A$2:$A$53,0)),"") -> 66474 | Q78: =IFERROR(K78/O78,"") -> 0.78263237 | R78: =IFERROR(I78-P78,"") -> -681 | S78: =IFERROR(R78/P78,"") -> -0.010244607
A79: University of West Georgia | B79: GA | C79: Carrollton | D79: 51.6 | E79: 1032 | F79: 7520 | G79: 6088 | H79: 17800 | I79: 49587 | J79: 43.1 | K79: 23970 | L79: 0 | M79: No | N79: =INDEX('State Mapping'!$B$2:$B$53,MATCH(B79,'State Mapping'!$A$2:$A$53,0)) -> Georgia | O79: =IFERROR(INDEX('State Premium Data'!$D$2:$D$53,MATCH(N79,'State Premium Data'!$A$2:$A$53,0)),"") -> 27365 | P79: =IFERROR(INDEX('State Premium Data'!$C$2:$C$53,MATCH(N79,'State Premium Data'!$A$2:$A$53,0)),"") -> 64185 | Q79: =IFERROR(K79/O79,"") -> 0.87593642 | R79: =IFERROR(I79-P79,"") -> -14598 | S79: =IFERROR(R79/P79,"") -> -0.22743632
A80: University of San Diego | B80: CA | C80: San Diego | D80: 52.4 | F80: 5671 | G80: 59486 | H80: 59486 | I80: 86522 | J80: 82.7 | K80: 22940 | L80: 0 | M80: No | N80: =INDEX('State Mapping'!$B$2:$B$53,MATCH(B80,'State Mapping'!$A$2:$A$53,0)) -> California | O80: =IFERROR(INDEX('State Premium Data'!$D$2:$D$53,MATCH(N80,'State Premium Data'!$A$2:$A$53,0)),"") -> 37475 | P80: =IFERROR(INDEX('State Premium Data'!$C$2:$C$53,MATCH(N80,'State Premium Data'!$A$2:$A$53,0)),"") -> 78278 | Q80: =IFERROR(K80/O80,"") -> 0.61214143 | R80: =IFERROR(I80-P80,"") -> 8244 | S80: =IFERROR(R80/P80,"") -> 0.10531695
A81: University of Connecticut | B81: CT | C81: Storrs | D81: 52.4 | E81: 1348 | F81: 19835 | G81: 21044 | H81: 43712 | I81: 73997 | J81: 83.5 | K81: 21500 | L81: 0 | M81: Yes | N81: =INDEX('State Mapping'!$B$2:$B$53,MATCH(B81,'State Mapping'!$A$2:$A$53,0)) -> Connecticut | O81: =IFERROR(INDEX('State Premium Data'!$D$2:$D$53,MATCH(N81,'State Premium Data'!$A$2:$A$53,0)),"") -> 33855 | P81: =IFERROR(INDEX('State Premium Data'!$C$2:$C$53,MATCH(N81,'State Premium Data'!$A$2:$A$53,0)),"") -> 75975 | Q81: =IFERROR(K81/O81,"") -> 0.63506129 | R81: =IFERROR(I81-P81,"") -> -1978 | S81: =IFERROR(R81/P81,"") -> -0.02603488
A82: University of North Florida | B82: FL | C82: Jacksonville | D82: 53.2 | E82: 1153 | F82: 13359 | G82: 6389 | H82: 20793 | I82: 56343 | J82: 68.7 | K82: 15531 | L82: 0 | M82: No | N82: =INDEX('State Mapping'!$B$2:$B$53,MATCH(B82,'State Mapping'!$A$2:$A$53,0)) -> Florida | O82: =IFERROR(INDEX('State Premium Data'!$D$2:$D$53,MATCH(N82,'State Premium Data'!$A$2:$A$53,0)),"") -> 21625 | P82: =IFERROR(INDEX('State Premium Data'!$C$2:$C$53,MATCH(N82,'State Premium Data'!$A$2:$A$53,0)),"") -> 58009 | Q82: =IFERROR(K82/O82,"") -> 0.71819653 | R82: =IFERROR(I82-P82,"") -> -1666 | S82: =IFERROR(R82/P82,"") -> -0.028719681
A83: CUNY Hunter College | B83: NY | C83: New York | D83: 53.8 | E83: 1280 | F83: 16289 | G83: 7382 | H83: 15332 | I83: 63163 | J83: 58.8 | K83: 11000 | L83: 0 | M83: No | N83: =INDEX('State Mapping'!$B$2:$B$53,MATCH(B83,'State Mapping'!$A$2:$A$53,0)) -> New York | O83: =IFERROR(INDEX('State Premium Data'!$D$2:$D$53,MATCH(N83,'State Premium Data'!$A$2:$A$53,0)),"") -> 34733 | P83: =IFERROR(INDEX('State Premium Data'!$C$2:$C$53,MATCH(N83,'State Premium Data'!$A$2:$A$53,0)),"") -> 74504 | Q83: =IFERROR(K83/O83,"") -> 0.3167017 | R83: =IFERROR(I83-P83,"") -> -11341 | S83: =IFERROR(R83/P83,"") -> -0.15222002
A84: University of Puerto Rico-Rio Piedras | B84: PR | C84: San Juan | D84: 54.6 | F84: 8572 | G84: 5354 | H84: 5354 | I84: 35723 | J84: 51.4 | K84: 5500 | L84: 0 | M84: No | N84: =INDEX('State Mapping'!$B$2:$B$53,MATCH(B84,'State Mapping'!$A$2:$A$53,0)) -> Puerto Rico | O84: =IFERROR(INDEX('State Premium Data'!$D$2:$D$53,MATCH(N84,'State Premium Data'!$A$2:$A$53,0)),"") -> 13605 | P84: =IFERROR(INDEX('State Premium Data'!$C$2:$C$53,MATCH(N84,'State Premium Data'!$A$2:$A$53,0)),"") -> 30562 | Q84: =IFERROR(K84/O84,"") -> 0.40426314 | R84: =IFERROR(I84-P84,"") -> 5161 | S84: =IFERROR(R84/P84,"") -> 0.16886984
A85: Florida International University | B85: FL | C85: Miami | D85: 54.7 | E85: 1163 | F85: 39508 | G85: 6565 | H85: 18964 | I85: 60249 | J85: 74.2 | K85: 16500 | L85: 0 | M85: No | N85: =INDEX('State Mapping'!$B$2:$B$53,MATCH(B85,'State Mapping'!$A$2:$A$53,0)) -> Florida | O85: =IFERROR(INDEX('State Premium Data'!$D$2:$D$53,MATCH(N85,'State Premium Data'!$A$2:$A$53,0)),"") -> 21625 | P85: =IFERROR(INDEX('State Premium Data'!$C$2:$C$53,MATCH(N85,'State Premium Data'!$A$2:$A$53,0)),"") -> 58009 | Q85: =IFERROR(K85/O85,"") -> 0.76300578 | R85: =IFERROR(I85-P85,"") -> 2240 | S85: =IFERROR(R85/P85,"") -> 0.038614698
A86: Virginia Polytechnic Institute and State University | B86: VA | C86: Blacksburg | D86: 54.8 | E86: 1364 | F86: 30923 | G86: 15948 | H86: 37764 | I86: 81698 | J86: 86.2 | K86: 21500 | L86: 0 | M86: No | N86: =INDEX('State Mapping'!$B$2:$B$53,MATCH(B86,'State Mapping'!$A$2:$A$53,0)) -> Virginia | O86: =IFERROR(INDEX('State Premium Data'!$D$2:$D$53,MATCH(N86,'State Premium Data'!$A$2:$A$53,0)),"") -> 33407 | P86: =IFERROR(INDEX('State Premium Data'!$C$2:$C$53,MATCH(N86,'State Premium Data'!$A$2:$A$53,0)),"") -> 74468 | Q86: =IFERROR(K86/O86,"") -> 0.64357769 | R86: =IFERROR(I86-P86,"") -> 7230 | S86: =IFERROR(R86/P86,"") -> 0.097088682
A87: Georgia State University | B87: GA | C87: Atlanta | D87: 55.4 | E87: 1076 | F87: 26623 | G87: 8664 | H87: 24840 | I87: 47384 | J87: 53.4 | K87: 20903 | L87: 0 | M87: No | N87: =INDEX('State Mapping'!$B$2:$B$53,MATCH(B87,'State Mapping'!$A$2:$A$53,0)) -> Georgia | O87: =IFERROR(INDEX('State Premium Data'!$D$2:$D$53,MATCH(N87,'State Premium Data'!$A$2:$A$53,0)),"") -> 27365 | P87: =IFERROR(INDEX('State Premium Data'!$C$2:$C$53,MATCH(N87,'State Premium Data'!$A$2:$A$53,0)),"") -> 64185 | Q87: =IFERROR(K87/O87,"") -> 0.76385894 | R87: =IFERROR(I87-P87,"") -> -16801 | S87: =IFERROR(R87/P87,"") -> -0.26175898
A88: University of Michigan-Dearborn | B88: MI | C88: Dearborn | D88: 55.6 | E88: 1115 | F88: 5952 | G88: 15640 | H88: 32896 | I88: 59649 | J88: 57.3 | K88: 22500 | L88: 0 | M88: Yes | N88: =INDEX('State Mapping'!$B$2:$B$53,MATCH(B88,'State Mapping'!$A$2:$A$53,0)) -> Michigan | O88: =IFERROR(INDEX('State Premium Data'!$D$2:$D$53,MATCH(N88,'State Premium Data'!$A$2:$A$53,0)),"") -> 27987 | P88: =IFERROR(INDEX('State Premium Data'!$C$2:$C$53,MATCH(N88,'State Premium Data'!$A$2:$A$53,0)),"") -> 64810 | Q88: =IFERROR(K88/O88,"") -> 0.80394469 | R88: =IFERROR(I88-P88,"") -> -5161 | S88: =IFERROR(R88/P88,"") -> -0.079632773
A89: Marist University | B89: NY | C89: Poughkeepsie | D89: 56.5 | E89: 1295 | F89: 5182 | G89: 47750 | H89: 47750 | I89: 77819 | J89: 79.7 | K89: 25000 | L89: 0 | M89: No | N89: =INDEX('State Mapping'!$B$2:$B$53,MATCH(B89,'State Mapping'!$A$2:$A$53,0)) -> New York | O89: =IFERROR(INDEX('State Premium Data'!$D$2:$D$53,MATCH(N89,'State Premium Data'!$A$2:$A$53,0)),"") -> 34733 | P89: =IFERROR(INDEX('State Premium Data'!$C$2:$C$53,MATCH(N89,'State Premium Data'!$A$2:$A$53,0)),"") -> 74504 | Q89: =IFERROR(K89/O89,"") -> 0.71977658 | R89: =IFERROR(I89-P89,"") -> 3315 | S89: =IFERROR(R89/P89,"") -> 0.044494255
A90: University of Puerto Rico-Mayaguez | B90: PR | C90: Mayaguez | D90: 56.5 | F90: 9539 | G90: 5274 | H90: 5274 | I90: 48992 | J90: 48 | K90: 8250 | L90: 0 | M90: No | N90: =INDEX('State Mapping'!$B$2:$B$53,MATCH(B90,'State Mapping'!$A$2:$A$53,0)) -> Puerto Rico | O90: =IFERROR(INDEX('State Premium Data'!$D$2:$D$53,MATCH(N90,'State Premium Data'!$A$2:$A$53,0)),"") -> 13605 | P90: =IFERROR(INDEX('State Premium Data'!$C$2:$C$53,MATCH(N90,'State Premium Data'!$A$2:$A$53,0)),"") -> 30562 | Q90: =IFERROR(K90/O90,"") -> 0.60639471 | R90: =IFERROR(I90-P90,"") -> 18430 | S90: =IFERROR(R90/P90,"") -> 0.60303645
A91: CUNY Lehman College | B91: NY | C91: Bronx | D91: 56.6 | E91: 970 | F91: 10696 | G91: 7410 | H91: 15360 | I91: 58013 | J91: 50.3 | K91: 10950 | L91: 0 | M91: No | N91: =INDEX('State Mapping'!$B$2:$B$53,MATCH(B91,'State Mapping'!$A$2:$A$53,0)) -> New York | O91: =IFERROR(INDEX('State Premium Data'!$D$2:$D$53,MATCH(N91,'State Premium Data'!$A$2:$A$53,0)),"") -> 34733 | P91: =IFERROR(INDEX('State Premium Data'!$C$2:$C$53,MATCH(N91,'State Premium Data'!$A$2:$A$53,0)),"") -> 74504 | Q91: =IFERROR(K91/O91,"") -> 0.31526214 | R91: =IFERROR(I91-P91,"") -> -16491 | S91: =IFERROR(R91/P91,"") -> -0.22134382
A92: CUNY John Jay College of Criminal Justice | B92: NY | C92: New York | D92: 57.1 | E92: 1080 | F92: 11590 | G92: 7470 | H92: 15420 | I92: 56195 | J92: 55.7 | K92: 11000 | L92: 0 | M92: No | N92: =INDEX('State Mapping'!$B$2:$B$53,MATCH(B92,'State Mapping'!$A$2:$A$53,0)) -> New York | O92: =IFERROR(INDEX('State Premium Data'!$D$2:$D$53,MATCH(N92,'State Premium Data'!$A$2:$A$53,0)),"") -> 34733 | P92: =IFERROR(INDEX('State Premium Data'!$C$2:$C$53,MATCH(N92,'State Premium Data'!$A$2:$A$53,0)),"") -> 74504 | Q92: =IFERROR(K92/O92,"") -> 0.3167017 | R92: =IFERROR(I92-P92,"") -> -18309 | S92: =IFERROR(R92/P92,"") -> -0.24574519
A93: Texas A&M University-College Station | B93: TX | C93: College Station | D93: 57.4 | E93: 1280 | F93: 59615 | G93: 13154 | H93: 40124 | I93: 72097 | J93: 83.9 | K93: 17804 | L93: 0 | M93: No | N93: =INDEX('State Mapping'!$B$2:$B$53,MATCH(B93,'State Mapping'!$A$2:$A$53,0)) -> Texas | O93: =IFERROR(INDEX('State Premium Data'!$D$2:$D$53,MATCH(N93,'State Premium Data'!$A$2:$A$53,0)),"") -> 29388 | P93: =IFERROR(INDEX('State Premium Data'!$C$2:$C$53,MATCH(N93,'State Premium Data'!$A$2:$A$53,0)),"") -> 66474 | Q93: =IFERROR(K93/O93,"") -> 0.60582551 | R93: =IFERROR(I93-P93,"") -> 5623 | S93: =IFERROR(R93/P93,"") -> 0.084589464
A94: Embry-Riddle Aeronautical University-Worldwide | B94: FL | C94: Daytona Beach | D94: 57.9 | E94: 1148 | F94: 9139 | G94: 12097 | H94: 12097 | I94: 84131 | J94: 21.1 | K94: 23666 | L94: 0 | M94: No | N94: =INDEX('State Mapping'!$B$2:$B$53,MATCH(B94,'State Mapping'!$A$2:$A$53,0)) -> Florida | O94: =IFERROR(INDEX('State Premium Data'!$D$2:$D$53,MATCH(N94,'State Premium Data'!$A$2:$A$53,0)),"") -> 21625 | P94: =IFERROR(INDEX('State Premium Data'!$C$2:$C$53,MATCH(N94,'State Premium Data'!$A$2:$A$53,0)),"") -> 58009 | Q94: =IFERROR(K94/O94,"") -> 1.0943815 | R94: =IFERROR(I94-P94,"") -> 26122 | S94: =IFERROR(R94/P94,"") -> 0.45030943
A95: Alabama A & M University | B95: AL | C95: Normal | D95: 58 | E95: 938 | F95: 6124 | G95: 10024 | H95: 18634 | I95: 40628 | J95: 26.3 | K95: 31000 | L95: 0 | M95: No | N95: =INDEX('State Mapping'!$B$2:$B$53,MATCH(B95,'State Mapping'!$A$2:$A$53,0)) -> Alabama | O95: =IFERROR(INDEX('State Premium Data'!$D$2:$D$53,MATCH(N95,'State Premium Data'!$A$2:$A$53,0)),"") -> 23541 | P95: =IFERROR(INDEX('State Premium Data'!$C$2:$C$53,MATCH(N95,'State Premium Data'!$A$2:$A$53,0)),"") -> 60156 | Q95: =IFERROR(K95/O95,"") -> 1.3168515 | R95: =IFERROR(I95-P95,"") -> -19528 | S95: =IFERROR(R95/P95,"") -> -0.32462265
A96: University of Pittsburgh-Pittsburgh Campus | B96: PA | C96: Pittsburgh | D96: 58.1 | E96: 1370 | F96: 20370 | G96: 21926 | H96: 41430 | I96: 66125 | J96: 84.9 | K96: 24250 | L96: 0 | M96: No | N96: =INDEX('State Mapping'!$B$2:$B$53,MATCH(B96,'State Mapping'!$A$2:$A$53,0)) -> Pennsylvania | O96: =IFERROR(INDEX('State Premium Data'!$D$2:$D$53,MATCH(N96,'State Premium Data'!$A$2:$A$53,0)),"") -> 25342 | P96: =IFERROR(INDEX('State Premium Data'!$C$2:$C$53,MATCH(N96,'State Premium Data'!$A$2:$A$53,0)),"") -> 65678 | Q96: =IFERROR(K96/O96,"") -> 0.95690948 | R96: =IFERROR(I96-P96,"") -> 447 | S96: =IFERROR(R96/P96,"") -> 0.006805932
A97: Rutgers University-New Brunswick | B97: NJ | C97: New Brunswick | D97: 58.1 | E97: 1410 | F97: 37751 | G97: 17929 | H97: 37441 | I97: 74479 | J97: 84.3 | K97: 21500 | L97: 1 | M97: No | N97: =INDEX('State Mapping'!$B$2:$B$53,MATCH(B97,'State Mapping'!$A$2:$A$53,0)) -> New Jersey | O97: =IFERROR(INDEX('State Premium Data'!$D$2:$D$53,MATCH(N97,'State Premium Data'!$A$2:$A$53,0)),"") -> 38586 | P97: =IFERROR(INDEX('State Premium Data'!$C$2:$C$53,MATCH(N97,'State Premium Data'!$A$2:$A$53,0)),"") -> 80114 | Q97: =IFERROR(K97/O97,"") -> 0.55719691 | R97: =IFERROR(I97-P97,"") -> -5635 | S97: =IFERROR(R97/P97,"") -> -0.070337269
A98: University of West Florida | B98: FL | C98: Pensacola | D98: 58.2 | E98: 1138 | F98: 9330 | G98: 6360 | H98: 19241 | I98: 49137 | J98: 60.3 | K98: 16624 | L98: 0 | M98: No | N98: =INDEX('State Mapping'!$B$2:$B$53,MATCH(B98,'State Mapping'!$A$2:$A$53,0)) -> Florida | O98: =IFERROR(INDEX('State Premium Data'!$D$2:$D$53,MATCH(N98,'State Premium Data'!$A$2:$A$53,0)),"") -> 21625 | P98: =IFERROR(INDEX('State Premium Data'!$C$2:$C$53,MATCH(N98,'State Premium Data'!$A$2:$A$53,0)),"") -> 58009 | Q98: =IFERROR(K98/O98,"") -> 0.76873988 | R98: =IFERROR(I98-P98,"") -> -8872 | S98: =IFERROR(R98/P98,"") -> -0.15294178
A99: CUNY Brooklyn College | B99: NY | C99: Brooklyn | D99: 58.4 | E99: 1140 | F99: 10543 | G99: 7452 | H99: 15402 | I99: 60752 | J99: 55.2 | K99: 11000 | L99: 0 | M99: No | N99: =INDEX('State Mapping'!$B$2:$B$53,MATCH(B99,'State Mapping'!$A$2:$A$53,0)) -> New York | O99: =IFERROR(INDEX('State Premium Data'!$D$2:$D$53,MATCH(N99,'State Premium Data'!$A$2:$A$53,0)),"") -> 34733 | P99: =IFERROR(INDEX('State Premium Data'!$C$2:$C$53,MATCH(N99,'State Premium Data'!$A$2:$A$53,0)),"") -> 74504 | Q99: =IFERROR(K99/O99,"") -> 0.3167017 | R99: =IFERROR(I99-P99,"") -> -13752 | S99: =IFERROR(R99/P99,"") -> -0.18458069
A100: Fordham University | B100: NY | C100: Bronx | D100: 59.3 | E100: 1418 | F100: 10512 | G100: 64915 | H100: 64915 | I100: 85569 | J100: 81.1 | K100: 24300 | L100: 0 | M100: No | N100: =INDEX('State Mapping'!$B$2:$B$53,MATCH(B100,'State Mapping'!$A$2:$A$53,0)) -> New York | O100: =IFERROR(INDEX('State Premium Data'!$D$2:$D$53,MATCH(N100,'State Premium Data'!$A$2:$A$53,0)),"") -> 34733 | P100: =IFERROR(INDEX('State Premium Data'!$C$2:$C$53,MATCH(N100,'State Premium Data'!$A$2:$A$53,0)),"") -> 74504 | Q100: =IFERROR(K100/O100,"") -> 0.69962284 | R100: =IFERROR(I100-P100,"") -> 11065 | S100: =IFERROR(R100/P100,"") -> 0.14851552
A101: University of Akron Main Campus | B101: OH | C101: Akron | D101: 59.7 | E101: 1081 | F101: 9052 | G101: 13135 | H101: 20815 | I101: 46600 | J101: 49.8 | K101: 23250 | L101: 0 | M101: Yes | N101: =INDEX('State Mapping'!$B$2:$B$53,MATCH(B101,'State Mapping'!$A$2:$A$53,0)) -> Ohio | O101: =IFERROR(INDEX('State Premium Data'!$D$2:$D$53,MATCH(N101,'State Premium Data'!$A$2:$A$53,0)),"") -> 26943 | P101: =IFERROR(INDEX('State Premium Data'!$C$2:$C$53,MATCH(N101,'State Premium Data'!$A$2:$A$53,0)),"") -> 64933 | Q101: =IFERROR(K101/O101,"") -> 0.86293286 | R101: =IFERROR(I101-P101,"") -> -18333 | S101: =IFERROR(R101/P101,"") -> -0.28233718
A102: University of Massachusetts-Amherst | B102: MA | C102: Amherst | D102: 59.7 | E102: 1423 | F102: 23671 | G102: 17772 | H102: 40449 | I102: 71631 | J102: 83.2 | K102: 22763 | L102: 0 | M102: No | N102: =INDEX('State Mapping'!$B$2:$B$53,MATCH(B102,'State Mapping'!$A$2:$A$53,0)) -> Massachusetts | O102: =IFERROR(INDEX('State Premium Data'!$D$2:$D$53,MATCH(N102,'State Premium Data'!$A$2:$A$53,0)),"") -> 36224 | P102: =IFERROR(INDEX('State Premium Data'!$C$2:$C$53,MATCH(N102,'State Premium Data'!$A$2:$A$53,0)),"") -> 79985 | Q102: =IFERROR(K102/O102,"") -> 0.62839554 | R102: =IFERROR(I102-P102,"") -> -8354 | S102: =IFERROR(R102/P102,"") -> -0.10444458
A103: State University of New York at Cortland | B103: NY | C103: Cortland | D103: 59.8 | F103: 5901 | G103: 8874 | H103: 18784 | I103: 60236 | J103: 68.1 | K103: 21500 | L103: 0 | M103: No | N103: =INDEX('State Mapping'!$B$2:$B$53,MATCH(B103,'State Mapping'!$A$2:$A$53,0)) -> New York | O103: =IFERROR(INDEX('State Premium Data'!$D$2:$D$53,MATCH(N103,'State Premium Data'!$A$2:$A$53,0)),"") -> 34733 | P103: =IFERROR(INDEX('State Premium Data'!$C$2:$C$53,MATCH(N103,'State Premium Data'!$A$2:$A$53,0)),"") -> 74504 | Q103: =IFERROR(K103/O103,"") -> 0.61900786 | R103: =IFERROR(I103-P103,"") -> -14268 | S103: =IFERROR(R103/P103,"") -> -0.1915065
A104: CUNY City College | B104: NY | C104: New York | D104: 60 | E104: 1260 | F104: 12505 | G104: 7340 | H104: 15290 | I104: 66039 | J104: 55.8 | K104: 11990 | L104: 0 | M104: No | N104: =INDEX('State Mapping'!$B$2:$B$53,MATCH(B104,'State Mapping'!$A$2:$A$53,0)) -> New York | O104: =IFERROR(INDEX('State Premium Data'!$D$2:$D$53,MATCH(N104,'State Premium Data'!$A$2:$A$53,0)),"") -> 34733 | P104: =IFERROR(INDEX('State Premium Data'!$C$2:$C$53,MATCH(N104,'State Premium Data'!$A$2:$A$53,0)),"") -> 74504 | Q104: =IFERROR(K104/O104,"") -> 0.34520485 | R104: =IFERROR(I104-P104,"") -> -8465 | S104: =IFERROR(R104/P104,"") -> -0.11361806
A105: College of Charleston | B105: SC | C105: Charleston | D105: 60 | E105: 1247 | F105: 10558 | G105: 12978 | H105: 38296 | I105: 56416 | J105: 65.4 | K105: 23250 | L105: 0 | M105: No | N105: =INDEX('State Mapping'!$B$2:$B$53,MATCH(B105,'State Mapping'!$A$2:$A$53,0)) -> South Carolina | O105: =IFERROR(INDEX('State Premium Data'!$D$2:$D$53,MATCH(N105,'State Premium Data'!$A$2:$A$53,0)),"") -> 23850 | P105: =IFERROR(INDEX('State Premium Data'!$C$2:$C$53,MATCH(N105,'State Premium Data'!$A$2:$A$53,0)),"") -> 60590 | Q105: =IFERROR(K105/O105,"") -> 0.97484277 | R105: =IFERROR(I105-P105,"") -> -4174 | S105: =IFERROR(R105/P105,"") -> -0.068889256
A106: University of South Carolina-Columbia | B106: SC | C106: Columbia | D106: 60.2 | E106: 1297 | F106: 29820 | G106: 12688 | H106: 35972 | I106: 62177 | J106: 78.3 | K106: 21500 | L106: 0 | M106: No | N106: =INDEX('State Mapping'!$B$2:$B$53,MATCH(B106,'State Mapping'!$A$2:$A$53,0)) -> South Carolina | O106: =IFERROR(INDEX('State Premium Data'!$D$2:$D$53,MATCH(N106,'State Premium Data'!$A$2:$A$53,0)),"") -> 23850 | P106: =IFERROR(INDEX('State Premium Data'!$C$2:$C$53,MATCH(N106,'State Premium Data'!$A$2:$A$53,0)),"") -> 60590 | Q106: =IFERROR(K106/O106,"") -> 0.90146751 | R106: =IFERROR(I106-P106,"") -> 1587 | S106: =IFERROR(R106/P106,"") -> 0.026192441
A107: Worcester Polytechnic Institute | B107: MA | C107: Worcester | D107: 60.2 | F107: 5447 | G107: 60965 | H107: 60965 | I107: 103470 | J107: 89.1 | K107: 27000 | L107: 0 | M107: No | N107: =INDEX('State Mapping'!$B$2:$B$53,MATCH(B107,'State Mapping'!$A$2:$A$53,0)) -> Massachusetts | O107: =IFERROR(INDEX('State Premium Data'!$D$2:$D$53,MATCH(N107,'State Premium Data'!$A$2:$A$53,0)),"") -> 36224 | P107: =IFERROR(INDEX('State Premium Data'!$C$2:$C$53,MATCH(N107,'State Premium Data'!$A$2:$A$53,0)),"") -> 79985 | Q107: =IFERROR(K107/O107,"") -> 0.74536219 | R107: =IFERROR(I107-P107,"") -> 23485 | S107: =IFERROR(R107/P107,"") -> 0.29361755
...

Sheet 3-School Comparison
A1: Harvard vs. Princeton vs. BYU — Debt & Earnings Comparison
A2: Debt-to-premium ratio and real vs. state-baseline earnings, benchmarked against the national average across all 200 schools.
A4: Metric | B4: Harvard University | C4: Princeton University | D4: Brigham Young University | E4: National Average (200 schools)
A5: Median Debt ($) | B5: =INDEX('College Data'!$K:$K,MATCH(B$4,'College Data'!$A:$A,0)) -> 14000 | C5: =INDEX('College Data'!$K:$K,MATCH(C$4,'College Data'!$A:$A,0)) -> 10320 | D5: =INDEX('College Data'!$K:$K,MATCH(D$4,'College Data'!$A:$A,0)) -> 11069 | E5: =AVERAGE('College Data'!$K$2:$K$201) -> 19824.92
A6: State College Wage Premium ($) | B6: =INDEX('College Data'!$O:$O,MATCH(B$4,'College Data'!$A:$A,0)) -> 36224 | C6: =INDEX('College Data'!$O:$O,MATCH(C$4,'College Data'!$A:$A,0)) -> 38586 | D6: =INDEX('College Data'!$O:$O,MATCH(D$4,'College Data'!$A:$A,0)) -> 21307 | E6: =AVERAGE('College Data'!$O$2:$O$201) -> 29759.19
A7: Debt-to-Premium Ratio | B7: =INDEX('College Data'!$Q:$Q,MATCH(B$4,'College Data'!$A:$A,0)) -> 0.3864841 | C7: =INDEX('College Data'!$Q:$Q,MATCH(C$4,'College Data'!$A:$A,0)) -> 0.26745452 | D7: =INDEX('College Data'!$Q:$Q,MATCH(D$4,'College Data'!$A:$A,0)) -> 0.51950063 | E7: =AVERAGE('College Data'!$Q$2:$Q$201) -> 0.7071609
A8: School Median Earnings, 10yr ($) | B8: =INDEX('College Data'!$I:$I,MATCH(B$4,'College Data'!$A:$A,0)) -> 101817 | C8: =INDEX('College Data'!$I:$I,MATCH(C$4,'College Data'!$A:$A,0)) -> 110066 | D8: =INDEX('College Data'!$I:$I,MATCH(D$4,'College Data'!$A:$A,0)) -> 75790 | E8: =AVERAGE('College Data'!$I$2:$I$201) -> 70114
A9: State Baseline Earnings - Bachelor's ($) | B9: =INDEX('College Data'!$P:$P,MATCH(B$4,'College Data'!$A:$A,0)) -> 79985 | C9: =INDEX('College Data'!$P:$P,MATCH(C$4,'College Data'!$A:$A,0)) -> 80114 | D9: =INDEX('College Data'!$P:$P,MATCH(D$4,'College Data'!$A:$A,0)) -> 63247 | E9: =AVERAGE('College Data'!$P$2:$P$201) -> 68800.67
A10: Real Earnings vs. State Baseline ($) | B10: =INDEX('College Data'!$R:$R,MATCH(B$4,'College Data'!$A:$A,0)) -> 21832 | C10: =INDEX('College Data'!$R:$R,MATCH(C$4,'College Data'!$A:$A,0)) -> 29952 | D10: =INDEX('College Data'!$R:$R,MATCH(D$4,'College Data'!$A:$A,0)) -> 12543 | E10: =AVERAGE('College Data'!$R$2:$R$201) -> 1313.33
A11: Real Earnings vs. State Baseline (%) | B11: =INDEX('College Data'!$S:$S,MATCH(B$4,'College Data'!$A:$A,0)) -> 0.27295118 | C11: =INDEX('College Data'!$S:$S,MATCH(C$4,'College Data'!$A:$A,0)) -> 0.37386724 | D11: =INDEX('College Data'!$S:$S,MATCH(D$4,'College Data'!$A:$A,0)) -> 0.19831771 | E11: =AVERAGE('College Data'!$S$2:$S$201) -> 0.023803204
A13: Legend
A14: Green = better than national average
A15: Red = worse than national average
A16: (For debt-to-premium, lower is better. For earnings-vs-baseline, higher is better.)
A18: Definitions
A19: Debt-to-Premium Ratio = Median Debt ÷ State College Wage Premium ($). Lower means the debt load is small relative to the wage boost a bachelor's degree earns in that state.
A20: State College Wage Premium ($) = state-level median bachelor's earnings minus median high-school-only earnings (college_premium_by_state.csv, Source: US Census / BEA).
A21: Real Earnings vs. State Baseline = School's Median Earnings (10yr) minus the state's average bachelor's-holder earnings. Shows whether a school's grads out-earn the typical bachelor's degree holder in that state.
A22: National Average = simple average across all 200 schools in college-data.csv, each matched to its state's premium data by state.
A24: Sources: college-data.csv (College Scorecard/US Dept of Education, Nobel Prize API, NCAA); college_premium_by_state.csv (US Census, Bureau of Economic Analysis).

Sheet Debt-to-Premium Ratio
A1: Debt-to-Premium Ratio
A2: Median Debt ÷ State College Wage Premium. Lower means less debt relative to the wage boost a bachelor's degree earns in that state.

Sheet Real Earnings vs Baseline
A1: Real Earnings vs. State Baseline ($)
A2: School's Median Earnings (10yr) minus the state's average bachelor's-holder earnings — how much each school's grads out-earn the typical bachelor's degree holder in that state.
